EECS 598/Task4_LUT.v
module Cosine_LUT (
    input [7:0] phase,
    output reg signed [7:0] cosine_value
);

    always @(*) begin 
        case (phase)
            8'd0: cosine_value = 8'b01111111;
            8'd1: cosine_value = 8'b01111111;
            8'd2: cosine_value = 8'b01111111;
            8'd3: cosine_value = 8'b01111111;
            8'd4: cosine_value = 8'b01111111;
            8'd5: cosine_value = 8'b01111111;
            8'd6: cosine_value = 8'b01111111;
            8'd7: cosine_value = 8'b01111110;
            8'd8: cosine_value = 8'b01111110;
            8'd9: cosine_value = 8'b01111101;
            8'd10: cosine_value = 8'b01111100;
            8'd11: cosine_value = 8'b01111011;
            8'd12: cosine_value = 8'b01111010;
            8'd13: cosine_value = 8'b01111010;
            8'd14: cosine_value = 8'b01111001;
            8'd15: cosine_value = 8'b01110111;
            8'd16: cosine_value = 8'b01110110;
            8'd17: cosine_value = 8'b01110101;
            8'd18: cosine_value = 8'b01110100;
            8'd19: cosine_value = 8'b01110010;
            8'd20: cosine_value = 8'b01110001;
            8'd21: cosine_value = 8'b01101111;
            8'd22: cosine_value = 8'b01101110;
            8'd23: cosine_value = 8'b01101100;
            8'd24: cosine_value = 8'b01101010;
            8'd25: cosine_value = 8'b01101001;
            8'd26: cosine_value = 8'b01100111;
            8'd27: cosine_value = 8'b01100101;
            8'd28: cosine_value = 8'b01100011;
            8'd29: cosine_value = 8'b01100001;
            8'd30: cosine_value = 8'b01011111;
            8'd31: cosine_value = 8'b01011101;
            8'd32: cosine_value = 8'b01011011;
            8'd33: cosine_value = 8'b01011000;
            8'd34: cosine_value = 8'b01010110;
            8'd35: cosine_value = 8'b01010100;
            8'd36: cosine_value = 8'b01010001;
            8'd37: cosine_value = 8'b01001111;
            8'd38: cosine_value = 8'b01001100;
            8'd39: cosine_value = 8'b01001010;
            8'd40: cosine_value = 8'b01000111;
            8'd41: cosine_value = 8'b01000100;
            8'd42: cosine_value = 8'b01000010;
            8'd43: cosine_value = 8'b00111111;
            8'd44: cosine_value = 8'b00111100;
            8'd45: cosine_value = 8'b00111010;
            8'd46: cosine_value = 8'b00110111;
            8'd47: cosine_value = 8'b00110100;
            8'd48: cosine_value = 8'b00110001;
            8'd49: cosine_value = 8'b00101110;
            8'd50: cosine_value = 8'b00101011;
            8'd51: cosine_value = 8'b00101000;
            8'd52: cosine_value = 8'b00100101;
            8'd53: cosine_value = 8'b00100010;
            8'd54: cosine_value = 8'b00011111;
            8'd55: cosine_value = 8'b00011100;
            8'd56: cosine_value = 8'b00011001;
            8'd57: cosine_value = 8'b00010110;
            8'd58: cosine_value = 8'b00010011;
            8'd59: cosine_value = 8'b00010000;
            8'd60: cosine_value = 8'b00001101;
            8'd61: cosine_value = 8'b00001001;
            8'd62: cosine_value = 8'b00000110;
            8'd63: cosine_value = 8'b00000011;
            8'd64: cosine_value = 8'b00000000;
            8'd65: cosine_value = 8'b11111101;
            8'd66: cosine_value = 8'b11111010;
            8'd67: cosine_value = 8'b11110111;
            8'd68: cosine_value = 8'b11110011;
            8'd69: cosine_value = 8'b11110000;
            8'd70: cosine_value = 8'b11101101;
            8'd71: cosine_value = 8'b11101010;
            8'd72: cosine_value = 8'b11100111;
            8'd73: cosine_value = 8'b11100100;
            8'd74: cosine_value = 8'b11100001;
            8'd75: cosine_value = 8'b11011110;
            8'd76: cosine_value = 8'b11011011;
            8'd77: cosine_value = 8'b11011000;
            8'd78: cosine_value = 8'b11010101;
            8'd79: cosine_value = 8'b11010010;
            8'd80: cosine_value = 8'b11001111;
            8'd81: cosine_value = 8'b11001100;
            8'd82: cosine_value = 8'b11001001;
            8'd83: cosine_value = 8'b11000110;
            8'd84: cosine_value = 8'b11000100;
            8'd85: cosine_value = 8'b11000001;
            8'd86: cosine_value = 8'b10111110;
            8'd87: cosine_value = 8'b10111100;
            8'd88: cosine_value = 8'b10111001;
            8'd89: cosine_value = 8'b10110110;
            8'd90: cosine_value = 8'b10110100;
            8'd91: cosine_value = 8'b10110001;
            8'd92: cosine_value = 8'b10101111;
            8'd93: cosine_value = 8'b10101100;
            8'd94: cosine_value = 8'b10101010;
            8'd95: cosine_value = 8'b10101000;
            8'd96: cosine_value = 8'b10100101;
            8'd97: cosine_value = 8'b10100011;
            8'd98: cosine_value = 8'b10100001;
            8'd99: cosine_value = 8'b10011111;
            8'd100: cosine_value = 8'b10011101;
            8'd101: cosine_value = 8'b10011011;
            8'd102: cosine_value = 8'b10011001;
            8'd103: cosine_value = 8'b10010111;
            8'd104: cosine_value = 8'b10010110;
            8'd105: cosine_value = 8'b10010100;
            8'd106: cosine_value = 8'b10010010;
            8'd107: cosine_value = 8'b10010001;
            8'd108: cosine_value = 8'b10001111;
            8'd109: cosine_value = 8'b10001110;
            8'd110: cosine_value = 8'b10001100;
            8'd111: cosine_value = 8'b10001011;
            8'd112: cosine_value = 8'b10001010;
            8'd113: cosine_value = 8'b10001001;
            8'd114: cosine_value = 8'b10000111;
            8'd115: cosine_value = 8'b10000110;
            8'd116: cosine_value = 8'b10000110;
            8'd117: cosine_value = 8'b10000101;
            8'd118: cosine_value = 8'b10000100;
            8'd119: cosine_value = 8'b10000011;
            8'd120: cosine_value = 8'b10000010;
            8'd121: cosine_value = 8'b10000010;
            8'd122: cosine_value = 8'b10000001;
            8'd123: cosine_value = 8'b10000001;
            8'd124: cosine_value = 8'b10000001;
            8'd125: cosine_value = 8'b10000000;
            8'd126: cosine_value = 8'b10000000;
            8'd127: cosine_value = 8'b10000000;
            8'd128: cosine_value = 8'b10000000;
            8'd129: cosine_value = 8'b10000000;
            8'd130: cosine_value = 8'b10000000;
            8'd131: cosine_value = 8'b10000000;
            8'd132: cosine_value = 8'b10000001;
            8'd133: cosine_value = 8'b10000001;
            8'd134: cosine_value = 8'b10000001;
            8'd135: cosine_value = 8'b10000010;
            8'd136: cosine_value = 8'b10000010;
            8'd137: cosine_value = 8'b10000011;
            8'd138: cosine_value = 8'b10000100;
            8'd139: cosine_value = 8'b10000101;
            8'd140: cosine_value = 8'b10000110;
            8'd141: cosine_value = 8'b10000110;
            8'd142: cosine_value = 8'b10000111;
            8'd143: cosine_value = 8'b10001001;
            8'd144: cosine_value = 8'b10001010;
            8'd145: cosine_value = 8'b10001011;
            8'd146: cosine_value = 8'b10001100;
            8'd147: cosine_value = 8'b10001110;
            8'd148: cosine_value = 8'b10001111;
            8'd149: cosine_value = 8'b10010001;
            8'd150: cosine_value = 8'b10010010;
            8'd151: cosine_value = 8'b10010100;
            8'd152: cosine_value = 8'b10010110;
            8'd153: cosine_value = 8'b10010111;
            8'd154: cosine_value = 8'b10011001;
            8'd155: cosine_value = 8'b10011011;
            8'd156: cosine_value = 8'b10011101;
            8'd157: cosine_value = 8'b10011111;
            8'd158: cosine_value = 8'b10100001;
            8'd159: cosine_value = 8'b10100011;
            8'd160: cosine_value = 8'b10100101;
            8'd161: cosine_value = 8'b10101000;
            8'd162: cosine_value = 8'b10101010;
            8'd163: cosine_value = 8'b10101100;
            8'd164: cosine_value = 8'b10101111;
            8'd165: cosine_value = 8'b10110001;
            8'd166: cosine_value = 8'b10110100;
            8'd167: cosine_value = 8'b10110110;
            8'd168: cosine_value = 8'b10111001;
            8'd169: cosine_value = 8'b10111100;
            8'd170: cosine_value = 8'b10111110;
            8'd171: cosine_value = 8'b11000001;
            8'd172: cosine_value = 8'b11000100;
            8'd173: cosine_value = 8'b11000110;
            8'd174: cosine_value = 8'b11001001;
            8'd175: cosine_value = 8'b11001100;
            8'd176: cosine_value = 8'b11001111;
            8'd177: cosine_value = 8'b11010010;
            8'd178: cosine_value = 8'b11010101;
            8'd179: cosine_value = 8'b11011000;
            8'd180: cosine_value = 8'b11011011;
            8'd181: cosine_value = 8'b11011110;
            8'd182: cosine_value = 8'b11100001;
            8'd183: cosine_value = 8'b11100100;
            8'd184: cosine_value = 8'b11100111;
            8'd185: cosine_value = 8'b11101010;
            8'd186: cosine_value = 8'b11101101;
            8'd187: cosine_value = 8'b11110000;
            8'd188: cosine_value = 8'b11110011;
            8'd189: cosine_value = 8'b11110111;
            8'd190: cosine_value = 8'b11111010;
            8'd191: cosine_value = 8'b11111101;
            8'd192: cosine_value = 8'b00000000;
            8'd193: cosine_value = 8'b00000011;
            8'd194: cosine_value = 8'b00000110;
            8'd195: cosine_value = 8'b00001001;
            8'd196: cosine_value = 8'b00001101;
            8'd197: cosine_value = 8'b00010000;
            8'd198: cosine_value = 8'b00010011;
            8'd199: cosine_value = 8'b00010110;
            8'd200: cosine_value = 8'b00011001;
            8'd201: cosine_value = 8'b00011100;
            8'd202: cosine_value = 8'b00011111;
            8'd203: cosine_value = 8'b00100010;
            8'd204: cosine_value = 8'b00100101;
            8'd205: cosine_value = 8'b00101000;
            8'd206: cosine_value = 8'b00101011;
            8'd207: cosine_value = 8'b00101110;
            8'd208: cosine_value = 8'b00110001;
            8'd209: cosine_value = 8'b00110100;
            8'd210: cosine_value = 8'b00110111;
            8'd211: cosine_value = 8'b00111010;
            8'd212: cosine_value = 8'b00111100;
            8'd213: cosine_value = 8'b00111111;
            8'd214: cosine_value = 8'b01000010;
            8'd215: cosine_value = 8'b01000100;
            8'd216: cosine_value = 8'b01000111;
            8'd217: cosine_value = 8'b01001010;
            8'd218: cosine_value = 8'b01001100;
            8'd219: cosine_value = 8'b01001111;
            8'd220: cosine_value = 8'b01010001;
            8'd221: cosine_value = 8'b01010100;
            8'd222: cosine_value = 8'b01010110;
            8'd223: cosine_value = 8'b01011000;
            8'd224: cosine_value = 8'b01011011;
            8'd225: cosine_value = 8'b01011101;
            8'd226: cosine_value = 8'b01011111;
            8'd227: cosine_value = 8'b01100001;
            8'd228: cosine_value = 8'b01100011;
            8'd229: cosine_value = 8'b01100101;
            8'd230: cosine_value = 8'b01100111;
            8'd231: cosine_value = 8'b01101001;
            8'd232: cosine_value = 8'b01101010;
            8'd233: cosine_value = 8'b01101100;
            8'd234: cosine_value = 8'b01101110;
            8'd235: cosine_value = 8'b01101111;
            8'd236: cosine_value = 8'b01110001;
            8'd237: cosine_value = 8'b01110010;
            8'd238: cosine_value = 8'b01110100;
            8'd239: cosine_value = 8'b01110101;
            8'd240: cosine_value = 8'b01110110;
            8'd241: cosine_value = 8'b01110111;
            8'd242: cosine_value = 8'b01111001;
            8'd243: cosine_value = 8'b01111010;
            8'd244: cosine_value = 8'b01111010;
            8'd245: cosine_value = 8'b01111011;
            8'd246: cosine_value = 8'b01111100;
            8'd247: cosine_value = 8'b01111101;
            8'd248: cosine_value = 8'b01111110;
            8'd249: cosine_value = 8'b01111110;
            8'd250: cosine_value = 8'b01111111;
            8'd251: cosine_value = 8'b01111111;
            8'd252: cosine_value = 8'b01111111;
            8'd253: cosine_value = 8'b01111111;
            8'd254: cosine_value = 8'b01111111;
            8'd255: cosine_value = 8'b01111111;
            default: cosine_value = 8'd0;
        endcase
    end
endmodule



module my_waveform_gem (
    input clk,
    input reset,
    input signed [8:0] control,
    output [7:0] my_sine_out,
    output [7:0] my_cosine_out
);

    reg signed [8:0] phase_change;
    

    always @(posedge clk) begin
        if (reset) 
            phase_change <= 9'sd0;
        else
            phase_change <= phase_change + control;
    end

    // Instantiation for cosine LUT output
    wire [7:0] lut_entry = phase_change [7:0];

    Cosine_LUT cos_ut (
        .phase(lut_entry),
        .cosine_value(my_cosine_out)
    );

    // Instantiation for sine LUT output
    Cosine_LUT sin_ut (
        .phase(lut_entry + 8'd64),  // 90-degree phase shift equivalent in terms of entry number
        .cosine_value(my_sine_out)
    );


endmodule


module my_controller (
    input clk, 
    input reset,
    input [7:0] period,
    output reg signed [8:0] control
);


    reg [13:0] counter;
    reg [13:0] half_period; // The number of the clock cycles
    reg signed [8:0] control_hf;
    reg signed [8:0] control_lf;
    reg switch; // Help to make switch between the two frequency


    // Initialize the control signal for each frequency (high for hf and low for lf)
    initial begin
        control_hf = 9'sd6;
        control_lf = 9'sd1;

    end


    // Alternates the frequency between 2.3 MHz and 0.3 MHz with the input period
    // reset cases - reset and period change
    always @(posedge clk) begin
        if (reset) begin
            counter <= 14'd0;
            switch <= 1'b0;
            control <= control_hf;
            half_period <= period * 8'd50;
        end else begin
        // Alternate the frequency when counter reaches the number of cycles for each half period
        if (counter >= half_period - 1) begin
            counter <= 14'd0;
            switch <= ~switch;
            control <= (~switch) ? control_lf : control_hf;
        end else begin
            counter <= counter + 14'd1;
        end
        // $display("counter number is:\t", counter);
        // $display("switch is:\t", switch);
        end
    end

endmodule

EECS 598/Task4b_tb.v
`timescale 1ns/1ns
module my_waveform_gem_tb;


    reg clk;
    reg reset;
    reg [7:0] period;
    wire signed [8:0] control;
    wire [7:0] my_sine_out;
    wire [7:0] my_cosine_out;
    integer outfile;


    // The instantiation of my waveform generator
    my_waveform_gem uut1 (
        .clk(clk),
        .reset(reset),
        .control(control),
        .my_sine_out(my_sine_out),
        .my_cosine_out(my_cosine_out)
    );

    my_controller uut2 (
        .clk(clk),
        .reset(reset),
        .period(period),
        .control(control)
    );

    // Create a file to store the sine and cosine outputs
    initial begin
        outfile = $fopen("output_data.txt", "w");
    end


    // 100 MHz clock - 10 ns clock period (clock cycle)
    initial clk = 0;
    always #5 clk = ~clk;

    initial begin
    // Dump the simulation result to a VCD file
        $dumpfile("waveform.vcd");
        $dumpvars(0, my_waveform_gem_tb);

        reset = 1;
        period = 8'd16;
        #10;
        reset = 0;
        
        #100000;

        // // Start test 1 - 3.29 MHz
        // control = 9'sd8;
        // #800;   // Roughly 2 time periods

        // // Start test 2 - -1.35 MHz
        // control = -9'sd3;
        // #2000;  // Roughly 2 time periods

        // // Start test 3 - 0.43 MHz
        // control = 9'sd1;
        // #5000; // Roughly 2 time periods

        $finish;

    end

    // Store the sine and cosine outputs to the file
    always @(posedge clk) begin
        if (!reset) begin
            $fwrite(outfile, "%d, %d\n", my_sine_out, my_cosine_out);
        end
    end



    endmodule

EECS 598/-1.35MHz.vcd
$date
	Sat Sep 21 20:53:49 2024
$end
$version
	GTKWave Analyzer v3.3.100 (w)1999-2019 BSI
$end
$timescale
	1ns
$end
$scope module my_waveform_gem_tb $end
$scope module uut $end
$var wire 8 " my_sine_out[7:0] $end
$var wire 8 # my_cosine_out[7:0] $end
$upscope $end
$upscope $end
$enddefinitions $end
$dumpvars
#0
bx #
bx "
#5
b0 "
b1111111 #
#15
b1001 "
#25
b10011 "
#35
b11100 "
b1111101 #
#45
b1111010 #
b100101 "
#55
b101110 "
b1110111 #
#65
b1110100 #
b110111 "
#75
b111111 "
b1101111 #
#85
b1101010 #
b1000111 "
#95
b1001111 "
b1100101 #
#105
b1011111 #
b1010110 "
#115
b1011101 "
b1011000 #
#125
b1010001 #
b1100011 "
#135
b1101001 "
b1001010 #
#145
b1000010 #
b1101110 "
#155
b1110010 "
b111010 #
#165
b110001 #
b1110110 "
#175
b1111010 "
b101000 #
#185
b11111 #
b1111100 "
#195
b1111110 "
b10110 #
#205
b1101 #
b1111111 "
#215
b11 #
#225
b11111010 #
#235
b11110000 #
#245
b11100111 #
b1111110 "
#255
b1111011 "
b11011110 #
#265
b11010101 #
b1111001 "
#275
b1110101 "
b11001100 #
#285
b11000100 #
b1110001 "
#295
b1101100 "
b10111100 #
#305
b10110100 #
b1100111 "
#315
b1100001 "
b10101100 #
#325
b10100101 #
b1011011 "
#335
b1010100 "
b10011111 #
#345
b10011001 #
b1001100 "
#355
b1000100 "
b10010100 #
#365
b10001111 #
b111100 "
#375
b110100 "
b10001011 #
#385
b10000111 #
b101011 "
#395
b100010 "
b10000101 #
#405
b10000010 #
b11001 "
#415
b10000 "
b10000001 #
#425
b10000000 #
b110 "
#435
b11111101 "
#445
b11110011 "
b10000001 #
#455
b10000010 #
b11101010 "
#465
b11100001 "
b10000100 #
#475
b10000110 #
b11011000 "
#485
b11001111 "
b10001010 #
#495
b10001110 #
b11000110 "
#505
b10111110 "
b10010010 #
#515
b10010111 #
b10110110 "
#525
b10101111 "
b10011101 #
#535
b10100011 #
b10101000 "
#545
b10100001 "
b10101010 #
#555
b10110001 #
b10011011 "
#565
b10010110 "
b10111001 #
#575
b11000001 #
b10010001 "
#585
b10001100 "
b11001001 #
#595
b11010010 #
b10001001 "
#605
b10000110 "
b11011011 #
#615
b11100100 #
b10000011 "
#625
b10000001 "
b11101101 #
#635
b11110111 #
b10000000 "
#645
b0 #
#655
b1001 #
#665
b10011 #
b10000001 "
#675
b10000011 "
b11100 #
#685
b100101 #
b10000110 "
#695
b10001001 "
b101110 #
#705
b110111 #
b10001100 "
#715
b10010001 "
b111111 #
#725
b1000111 #
b10010110 "
#735
b10011011 "
b1001111 #
#745
b1010110 #
b10100001 "
#755
b10101000 "
b1011101 #
#765
b1100011 #
b10101111 "
#775
b10110110 "
b1101001 #
#785
b1101110 #
b10111110 "
#795
b11000110 "
b1110010 #
#805
b1110110 #
b11001111 "
#815
b11011000 "
b1111010 #
#825
b1111100 #
b11100001 "
#835
b11101010 "
b1111110 #
#845
b1111111 #
b11110011 "
#855
b11111101 "
#865
b110 "
#875
b10000 "
#885
b11001 "
b1111110 #
#895
b1111011 #
b100010 "
#905
b101011 "
b1111001 #
#915
b1110101 #
b110100 "
#925
b111100 "
b1110001 #
#935
b1101100 #
b1000100 "
#945
b1001100 "
b1100111 #
#955
b1100001 #
b1010100 "
#965
b1011011 "
b1011011 #
#975
b1010100 #
b1100001 "
#985
b1100111 "
b1001100 #
#995
b1000100 #
b1101100 "
#1005
b1110001 "
b111100 #
#1015
b110100 #
b1110101 "
#1025
b1111001 "
b101011 #
#1035
b100010 #
b1111011 "
#1045
b1111110 "
b11001 #
#1055
b10000 #
b1111111 "
#1065
b110 #
#1075
b11111101 #
#1085
b11110011 #
#1095
b11101010 #
b1111110 "
#1105
b1111100 "
b11100001 #
#1115
b11011000 #
b1111010 "
#1125
b1110110 "
b11001111 #
#1135
b11000110 #
b1110010 "
#1145
b1101110 "
b10111110 #
#1155
b10110110 #
b1101001 "
#1165
b1100011 "
b10101111 #
#1175
b10101000 #
b1011101 "
#1185
b1010110 "
b10100001 #
#1195
b10011011 #
b1001111 "
#1205
b1000111 "
b10010110 #
#1215
b10010001 #
b111111 "
#1225
b110111 "
b10001100 #
#1235
b10001001 #
b101110 "
#1245
b100101 "
b10000110 #
#1255
b10000011 #
b11100 "
#1265
b10011 "
b10000001 #
#1275
b10000000 #
b1001 "
#1285
b0 "
#1295
b11110111 "
#1305
b11101101 "
b10000001 #
#1315
b10000011 #
b11100100 "
#1325
b11011011 "
b10000110 #
#1335
b10001001 #
b11010010 "
#1345
b11001001 "
b10001100 #
#1355
b10010001 #
b11000001 "
#1365
b10111001 "
b10010110 #
#1375
b10011011 #
b10110001 "
#1385
b10101010 "
b10100001 #
#1395
b10101000 #
b10100011 "
#1405
b10011101 "
b10101111 #
#1415
b10110110 #
b10010111 "
#1425
b10010010 "
b10111110 #
#1435
b11000110 #
b10001110 "
#1445
b10001010 "
b11001111 #
#1455
b11011000 #
b10000110 "
#1465
b10000100 "
b11100001 #
#1475
b11101010 #
b10000010 "
#1485
b10000001 "
b11110011 #
#1495
b11111101 #
b10000000 "
#1505
b110 #
#1515
b10000 #
b10000001 "
#1525
b10000010 "
b11001 #
#1535
b100010 #
b10000101 "
#1545
b10000111 "
b101011 #
#1555
b110100 #
b10001011 "
#1565
b10001111 "
b111100 #
#1575
b1000100 #
b10010100 "
#1585
b10011001 "
b1001100 #
#1595
b1010100 #
b10011111 "
#1605
b10100101 "
b1011011 #
#1615
b1100001 #
b10101100 "
#1625
b10110100 "
b1100111 #
#1635
b1101100 #
b10111100 "
#1645
b11000100 "
b1110001 #
#1655
b1110101 #
b11001100 "
#1665
b11010101 "
b1111001 #
#1675
b1111011 #
b11011110 "
#1685
b11100111 "
b1111110 #
#1695
b1111111 #
b11110000 "
#1705
b11111010 "
#1715
b11 "
#1725
b1101 "
#1735
b10110 "
b1111110 #
#1745
b1111100 #
b11111 "
#1755
b101000 "
b1111010 #
#1765
b1110110 #
b110001 "
#1775
b111010 "
b1110010 #
#1785
b1101110 #
b1000010 "
#1795
b1001010 "
b1101001 #
#1805
b1100011 #
b1010001 "
#1815
b1011000 "
b1011101 #
#1825
b1010110 #
b1011111 "
#1835
b1100101 "
b1001111 #
#1845
b1000111 #
b1101010 "
#1855
b1101111 "
b111111 #
#1865
b110111 #
b1110100 "
#1875
b1110111 "
b101110 #
#1885
b100101 #
b1111010 "
#1895
b1111101 "
b11100 #
#1905
b10011 #
b1111111 "
#1915
b1001 #
#1925
b0 #
#1935
b11110111 #
#1945
b11101101 #
#1955
b11100100 #
b1111101 "
#1965
b1111010 "
b11011011 #
#1975
b11010010 #
b1110111 "
#1985
b1110100 "
b11001001 #
#1995
b11000001 #
b1101111 "
#2005
b1101010 "
b10111001 #
