EECS 598/Task4_LUT.v
module Cosine_LUT (
    input [7:0] phase,
    output reg signed [7:0] cosine_value
);

    always @(*) begin 
        case (phase)
            8'd0: cosine_value = 8'b01111111;
            8'd1: cosine_value = 8'b01111111;
            8'd2: cosine_value = 8'b01111111;
            8'd3: cosine_value = 8'b01111111;
            8'd4: cosine_value = 8'b01111111;
            8'd5: cosine_value = 8'b01111111;
            8'd6: cosine_value = 8'b01111111;
            8'd7: cosine_value = 8'b01111110;
            8'd8: cosine_value = 8'b01111110;
            8'd9: cosine_value = 8'b01111101;
            8'd10: cosine_value = 8'b01111100;
            8'd11: cosine_value = 8'b01111011;
            8'd12: cosine_value = 8'b01111010;
            8'd13: cosine_value = 8'b01111010;
            8'd14: cosine_value = 8'b01111001;
            8'd15: cosine_value = 8'b01110111;
            8'd16: cosine_value = 8'b01110110;
            8'd17: cosine_value = 8'b01110101;
            8'd18: cosine_value = 8'b01110100;
            8'd19: cosine_value = 8'b01110010;
            8'd20: cosine_value = 8'b01110001;
            8'd21: cosine_value = 8'b01101111;
            8'd22: cosine_value = 8'b01101110;
            8'd23: cosine_value = 8'b01101100;
            8'd24: cosine_value = 8'b01101010;
            8'd25: cosine_value = 8'b01101001;
            8'd26: cosine_value = 8'b01100111;
            8'd27: cosine_value = 8'b01100101;
            8'd28: cosine_value = 8'b01100011;
            8'd29: cosine_value = 8'b01100001;
            8'd30: cosine_value = 8'b01011111;
            8'd31: cosine_value = 8'b01011101;
            8'd32: cosine_value = 8'b01011011;
            8'd33: cosine_value = 8'b01011000;
            8'd34: cosine_value = 8'b01010110;
            8'd35: cosine_value = 8'b01010100;
            8'd36: cosine_value = 8'b01010001;
            8'd37: cosine_value = 8'b01001111;
            8'd38: cosine_value = 8'b01001100;
            8'd39: cosine_value = 8'b01001010;
            8'd40: cosine_value = 8'b01000111;
            8'd41: cosine_value = 8'b01000100;
            8'd42: cosine_value = 8'b01000010;
            8'd43: cosine_value = 8'b00111111;
            8'd44: cosine_value = 8'b00111100;
            8'd45: cosine_value = 8'b00111010;
            8'd46: cosine_value = 8'b00110111;
            8'd47: cosine_value = 8'b00110100;
            8'd48: cosine_value = 8'b00110001;
            8'd49: cosine_value = 8'b00101110;
            8'd50: cosine_value = 8'b00101011;
            8'd51: cosine_value = 8'b00101000;
            8'd52: cosine_value = 8'b00100101;
            8'd53: cosine_value = 8'b00100010;
            8'd54: cosine_value = 8'b00011111;
            8'd55: cosine_value = 8'b00011100;
            8'd56: cosine_value = 8'b00011001;
            8'd57: cosine_value = 8'b00010110;
            8'd58: cosine_value = 8'b00010011;
            8'd59: cosine_value = 8'b00010000;
            8'd60: cosine_value = 8'b00001101;
            8'd61: cosine_value = 8'b00001001;
            8'd62: cosine_value = 8'b00000110;
            8'd63: cosine_value = 8'b00000011;
            8'd64: cosine_value = 8'b00000000;
            8'd65: cosine_value = 8'b11111101;
            8'd66: cosine_value = 8'b11111010;
            8'd67: cosine_value = 8'b11110111;
            8'd68: cosine_value = 8'b11110011;
            8'd69: cosine_value = 8'b11110000;
            8'd70: cosine_value = 8'b11101101;
            8'd71: cosine_value = 8'b11101010;
            8'd72: cosine_value = 8'b11100111;
            8'd73: cosine_value = 8'b11100100;
            8'd74: cosine_value = 8'b11100001;
            8'd75: cosine_value = 8'b11011110;
            8'd76: cosine_value = 8'b11011011;
            8'd77: cosine_value = 8'b11011000;
            8'd78: cosine_value = 8'b11010101;
            8'd79: cosine_value = 8'b11010010;
            8'd80: cosine_value = 8'b11001111;
            8'd81: cosine_value = 8'b11001100;
            8'd82: cosine_value = 8'b11001001;
            8'd83: cosine_value = 8'b11000110;
            8'd84: cosine_value = 8'b11000100;
            8'd85: cosine_value = 8'b11000001;
            8'd86: cosine_value = 8'b10111110;
            8'd87: cosine_value = 8'b10111100;
            8'd88: cosine_value = 8'b10111001;
            8'd89: cosine_value = 8'b10110110;
            8'd90: cosine_value = 8'b10110100;
            8'd91: cosine_value = 8'b10110001;
            8'd92: cosine_value = 8'b10101111;
            8'd93: cosine_value = 8'b10101100;
            8'd94: cosine_value = 8'b10101010;
            8'd95: cosine_value = 8'b10101000;
            8'd96: cosine_value = 8'b10100101;
            8'd97: cosine_value = 8'b10100011;
            8'd98: cosine_value = 8'b10100001;
            8'd99: cosine_value = 8'b10011111;
            8'd100: cosine_value = 8'b10011101;
            8'd101: cosine_value = 8'b10011011;
            8'd102: cosine_value = 8'b10011001;
            8'd103: cosine_value = 8'b10010111;
            8'd104: cosine_value = 8'b10010110;
            8'd105: cosine_value = 8'b10010100;
            8'd106: cosine_value = 8'b10010010;
            8'd107: cosine_value = 8'b10010001;
            8'd108: cosine_value = 8'b10001111;
            8'd109: cosine_value = 8'b10001110;
            8'd110: cosine_value = 8'b10001100;
            8'd111: cosine_value = 8'b10001011;
            8'd112: cosine_value = 8'b10001010;
            8'd113: cosine_value = 8'b10001001;
            8'd114: cosine_value = 8'b10000111;
            8'd115: cosine_value = 8'b10000110;
            8'd116: cosine_value = 8'b10000110;
            8'd117: cosine_value = 8'b10000101;
            8'd118: cosine_value = 8'b10000100;
            8'd119: cosine_value = 8'b10000011;
            8'd120: cosine_value = 8'b10000010;
            8'd121: cosine_value = 8'b10000010;
            8'd122: cosine_value = 8'b10000001;
            8'd123: cosine_value = 8'b10000001;
            8'd124: cosine_value = 8'b10000001;
            8'd125: cosine_value = 8'b10000000;
            8'd126: cosine_value = 8'b10000000;
            8'd127: cosine_value = 8'b10000000;
            8'd128: cosine_value = 8'b10000000;
            8'd129: cosine_value = 8'b10000000;
            8'd130: cosine_value = 8'b10000000;
            8'd131: cosine_value = 8'b10000000;
            8'd132: cosine_value = 8'b10000001;
            8'd133: cosine_value = 8'b10000001;
            8'd134: cosine_value = 8'b10000001;
            8'd135: cosine_value = 8'b10000010;
            8'd136: cosine_value = 8'b10000010;
            8'd137: cosine_value = 8'b10000011;
            8'd138: cosine_value = 8'b10000100;
            8'd139: cosine_value = 8'b10000101;
            8'd140: cosine_value = 8'b10000110;
            8'd141: cosine_value = 8'b10000110;
            8'd142: cosine_value = 8'b10000111;
            8'd143: cosine_value = 8'b10001001;
            8'd144: cosine_value = 8'b10001010;
            8'd145: cosine_value = 8'b10001011;
            8'd146: cosine_value = 8'b10001100;
            8'd147: cosine_value = 8'b10001110;
            8'd148: cosine_value = 8'b10001111;
            8'd149: cosine_value = 8'b10010001;
            8'd150: cosine_value = 8'b10010010;
            8'd151: cosine_value = 8'b10010100;
            8'd152: cosine_value = 8'b10010110;
            8'd153: cosine_value = 8'b10010111;
            8'd154: cosine_value = 8'b10011001;
            8'd155: cosine_value = 8'b10011011;
            8'd156: cosine_value = 8'b10011101;
            8'd157: cosine_value = 8'b10011111;
            8'd158: cosine_value = 8'b10100001;
            8'd159: cosine_value = 8'b10100011;
            8'd160: cosine_value = 8'b10100101;
            8'd161: cosine_value = 8'b10101000;
            8'd162: cosine_value = 8'b10101010;
            8'd163: cosine_value = 8'b10101100;
            8'd164: cosine_value = 8'b10101111;
            8'd165: cosine_value = 8'b10110001;
            8'd166: cosine_value = 8'b10110100;
            8'd167: cosine_value = 8'b10110110;
            8'd168: cosine_value = 8'b10111001;
            8'd169: cosine_value = 8'b10111100;
            8'd170: cosine_value = 8'b10111110;
            8'd171: cosine_value = 8'b11000001;
            8'd172: cosine_value = 8'b11000100;
            8'd173: cosine_value = 8'b11000110;
            8'd174: cosine_value = 8'b11001001;
            8'd175: cosine_value = 8'b11001100;
            8'd176: cosine_value = 8'b11001111;
            8'd177: cosine_value = 8'b11010010;
            8'd178: cosine_value = 8'b11010101;
            8'd179: cosine_value = 8'b11011000;
            8'd180: cosine_value = 8'b11011011;
            8'd181: cosine_value = 8'b11011110;
            8'd182: cosine_value = 8'b11100001;
            8'd183: cosine_value = 8'b11100100;
            8'd184: cosine_value = 8'b11100111;
            8'd185: cosine_value = 8'b11101010;
            8'd186: cosine_value = 8'b11101101;
            8'd187: cosine_value = 8'b11110000;
            8'd188: cosine_value = 8'b11110011;
            8'd189: cosine_value = 8'b11110111;
            8'd190: cosine_value = 8'b11111010;
            8'd191: cosine_value = 8'b11111101;
            8'd192: cosine_value = 8'b00000000;
            8'd193: cosine_value = 8'b00000011;
            8'd194: cosine_value = 8'b00000110;
            8'd195: cosine_value = 8'b00001001;
            8'd196: cosine_value = 8'b00001101;
            8'd197: cosine_value = 8'b00010000;
            8'd198: cosine_value = 8'b00010011;
            8'd199: cosine_value = 8'b00010110;
            8'd200: cosine_value = 8'b00011001;
            8'd201: cosine_value = 8'b00011100;
            8'd202: cosine_value = 8'b00011111;
            8'd203: cosine_value = 8'b00100010;
            8'd204: cosine_value = 8'b00100101;
            8'd205: cosine_value = 8'b00101000;
            8'd206: cosine_value = 8'b00101011;
            8'd207: cosine_value = 8'b00101110;
            8'd208: cosine_value = 8'b00110001;
            8'd209: cosine_value = 8'b00110100;
            8'd210: cosine_value = 8'b00110111;
            8'd211: cosine_value = 8'b00111010;
            8'd212: cosine_value = 8'b00111100;
            8'd213: cosine_value = 8'b00111111;
            8'd214: cosine_value = 8'b01000010;
            8'd215: cosine_value = 8'b01000100;
            8'd216: cosine_value = 8'b01000111;
            8'd217: cosine_value = 8'b01001010;
            8'd218: cosine_value = 8'b01001100;
            8'd219: cosine_value = 8'b01001111;
            8'd220: cosine_value = 8'b01010001;
            8'd221: cosine_value = 8'b01010100;
            8'd222: cosine_value = 8'b01010110;
            8'd223: cosine_value = 8'b01011000;
            8'd224: cosine_value = 8'b01011011;
            8'd225: cosine_value = 8'b01011101;
            8'd226: cosine_value = 8'b01011111;
            8'd227: cosine_value = 8'b01100001;
            8'd228: cosine_value = 8'b01100011;
            8'd229: cosine_value = 8'b01100101;
            8'd230: cosine_value = 8'b01100111;
            8'd231: cosine_value = 8'b01101001;
            8'd232: cosine_value = 8'b01101010;
            8'd233: cosine_value = 8'b01101100;
            8'd234: cosine_value = 8'b01101110;
            8'd235: cosine_value = 8'b01101111;
            8'd236: cosine_value = 8'b01110001;
            8'd237: cosine_value = 8'b01110010;
            8'd238: cosine_value = 8'b01110100;
            8'd239: cosine_value = 8'b01110101;
            8'd240: cosine_value = 8'b01110110;
            8'd241: cosine_value = 8'b01110111;
            8'd242: cosine_value = 8'b01111001;
            8'd243: cosine_value = 8'b01111010;
            8'd244: cosine_value = 8'b01111010;
            8'd245: cosine_value = 8'b01111011;
            8'd246: cosine_value = 8'b01111100;
            8'd247: cosine_value = 8'b01111101;
            8'd248: cosine_value = 8'b01111110;
            8'd249: cosine_value = 8'b01111110;
            8'd250: cosine_value = 8'b01111111;
            8'd251: cosine_value = 8'b01111111;
            8'd252: cosine_value = 8'b01111111;
            8'd253: cosine_value = 8'b01111111;
            8'd254: cosine_value = 8'b01111111;
            8'd255: cosine_value = 8'b01111111;
            default: cosine_value = 8'd0;
        endcase
    end
endmodule



module my_waveform_gem (
    input clk,
    input reset,
    input signed [8:0] control,
    output [7:0] my_sine_out,
    output [7:0] my_cosine_out
);

    reg signed [8:0] phase_change;
    

    always @(posedge clk) begin
        if (reset) 
            phase_change <= 9'sd0;
        else
            phase_change <= phase_change + control;
    end

    // Instantiation for cosine LUT output
    wire [7:0] lut_entry = phase_change [7:0];

    Cosine_LUT cos_ut (
        .phase(lut_entry),
        .cosine_value(my_cosine_out)
    );

    // Instantiation for sine LUT output
    Cosine_LUT sin_ut (
        .phase(lut_entry + 8'd64),  // 90-degree phase shift equivalent in terms of entry number
        .cosine_value(my_sine_out)
    );


endmodule


module my_controller (
    input clk, 
    input reset,
    input [7:0] period,
    output reg signed [8:0] control
);


    reg [13:0] counter;
    reg [13:0] half_period; // The number of the clock cycles
    reg signed [8:0] control_hf;
    reg signed [8:0] control_lf;
    reg switch; // Help to make switch between the two frequency


    // Initialize the control signal for each frequency (high for hf and low for lf)
    initial begin
        control_hf = 9'sd6;
        control_lf = 9'sd1;

    end


    // Alternates the frequency between 2.3 MHz and 0.3 MHz with the input period
    // reset cases - reset and period change
    always @(posedge clk) begin
        if (reset) begin
            counter <= 14'd0;
            switch <= 1'b0;
            control <= control_hf;
            half_period <= period * 8'd50;
        end else begin
        // Alternate the frequency when counter reaches the number of cycles for each half period
        if (counter >= half_period - 1) begin
            counter <= 14'd0;
            switch <= ~switch;
            control <= (~switch) ? control_lf : control_hf;
        end else begin
            counter <= counter + 14'd1;
        end
        // $display("counter number is:\t", counter);
        // $display("switch is:\t", switch);
        end
    end

endmodule

EECS 598/Task4b_tb.v
`timescale 1ns/1ns
module my_waveform_gem_tb;


    reg clk;
    reg reset;
    reg [7:0] period;
    wire signed [8:0] control;
    wire [7:0] my_sine_out;
    wire [7:0] my_cosine_out;
    integer outfile;


    // The instantiation of my waveform generator
    my_waveform_gem uut1 (
        .clk(clk),
        .reset(reset),
        .control(control),
        .my_sine_out(my_sine_out),
        .my_cosine_out(my_cosine_out)
    );

    my_controller uut2 (
        .clk(clk),
        .reset(reset),
        .period(period),
        .control(control)
    );

    // Create a file to store the sine and cosine outputs
    initial begin
        outfile = $fopen("output_data.txt", "w");
    end


    // 100 MHz clock - 10 ns clock period (clock cycle)
    initial clk = 0;
    always #5 clk = ~clk;

    initial begin
    // Dump the simulation result to a VCD file
        $dumpfile("waveform.vcd");
        $dumpvars(0, my_waveform_gem_tb);

        reset = 1;
        period = 8'd16;
        #10;
        reset = 0;
        
        #100000;

        // // Start test 1 - 3.29 MHz
        // control = 9'sd8;
        // #800;   // Roughly 2 time periods

        // // Start test 2 - -1.35 MHz
        // control = -9'sd3;
        // #2000;  // Roughly 2 time periods

        // // Start test 3 - 0.43 MHz
        // control = 9'sd1;
        // #5000; // Roughly 2 time periods

        $finish;

    end

    // Store the sine and cosine outputs to the file
    always @(posedge clk) begin
        if (!reset) begin
            $fwrite(outfile, "%d, %d\n", my_sine_out, my_cosine_out);
        end
    end



    endmodule

EECS 598/0.43MHz.vcd
$date
	Sat Sep 21 21:00:31 2024
$end
$version
	GTKWave Analyzer v3.3.100 (w)1999-2019 BSI
$end
$timescale
	1ns
$end
$scope module my_waveform_gem_tb $end
$scope module uut $end
$var wire 8 # my_cosine_out[7:0] $end
$var wire 8 " my_sine_out[7:0] $end
$upscope $end
$upscope $end
$enddefinitions $end
$dumpvars
#0
bx "
bx #
#5
b1111111 #
b0 "
#15
b11111101 "
#25
b11111010 "
#35
b11110111 "
#45
b11110011 "
#55
b11110000 "
#65
b11101101 "
#75
b11101010 "
b1111110 #
#85
b11100111 "
#95
b11100100 "
b1111101 #
#105
b1111100 #
b11100001 "
#115
b11011110 "
b1111011 #
#125
b1111010 #
b11011011 "
#135
b11011000 "
#145
b11010101 "
b1111001 #
#155
b1110111 #
b11010010 "
#165
b11001111 "
b1110110 #
#175
b1110101 #
b11001100 "
#185
b11001001 "
b1110100 #
#195
b1110010 #
b11000110 "
#205
b11000100 "
b1110001 #
#215
b1101111 #
b11000001 "
#225
b10111110 "
b1101110 #
#235
b1101100 #
b10111100 "
#245
b10111001 "
b1101010 #
#255
b1101001 #
b10110110 "
#265
b10110100 "
b1100111 #
#275
b1100101 #
b10110001 "
#285
b10101111 "
b1100011 #
#295
b1100001 #
b10101100 "
#305
b10101010 "
b1011111 #
#315
b1011101 #
b10101000 "
#325
b10100101 "
b1011011 #
#335
b1011000 #
b10100011 "
#345
b10100001 "
b1010110 #
#355
b1010100 #
b10011111 "
#365
b10011101 "
b1010001 #
#375
b1001111 #
b10011011 "
#385
b10011001 "
b1001100 #
#395
b1001010 #
b10010111 "
#405
b10010110 "
b1000111 #
#415
b1000100 #
b10010100 "
#425
b10010010 "
b1000010 #
#435
b111111 #
b10010001 "
#445
b10001111 "
b111100 #
#455
b111010 #
b10001110 "
#465
b10001100 "
b110111 #
#475
b110100 #
b10001011 "
#485
b10001010 "
b110001 #
#495
b101110 #
b10001001 "
#505
b10000111 "
b101011 #
#515
b101000 #
b10000110 "
#525
b100101 #
#535
b100010 #
b10000101 "
#545
b10000100 "
b11111 #
#555
b11100 #
b10000011 "
#565
b10000010 "
b11001 #
#575
b10110 #
#585
b10011 #
b10000001 "
#595
b10000 #
#605
b1101 #
#615
b1001 #
b10000000 "
#625
b110 #
#635
b11 #
#645
b0 #
#655
b11111101 #
#665
b11111010 #
#675
b11110111 #
#685
b11110011 #
b10000001 "
#695
b11110000 #
#705
b11101101 #
#715
b11101010 #
b10000010 "
#725
b11100111 #
#735
b11100100 #
b10000011 "
#745
b10000100 "
b11100001 #
#755
b11011110 #
b10000101 "
#765
b10000110 "
b11011011 #
#775
b11011000 #
#785
b11010101 #
b10000111 "
#795
b10001001 "
b11010010 #
#805
b11001111 #
b10001010 "
#815
b10001011 "
b11001100 #
#825
b11001001 #
b10001100 "
#835
b10001110 "
b11000110 #
#845
b11000100 #
b10001111 "
#855
b10010001 "
b11000001 #
#865
b10111110 #
b10010010 "
#875
b10010100 "
b10111100 #
#885
b10111001 #
b10010110 "
#895
b10010111 "
b10110110 #
#905
b10110100 #
b10011001 "
#915
b10011011 "
b10110001 #
#925
b10101111 #
b10011101 "
#935
b10011111 "
b10101100 #
#945
b10101010 #
b10100001 "
#955
b10100011 "
b10101000 #
#965
b10100101 #
b10100101 "
#975
b10101000 "
b10100011 #
#985
b10100001 #
b10101010 "
#995
b10101100 "
b10011111 #
#1005
b10011101 #
b10101111 "
#1015
b10110001 "
b10011011 #
#1025
b10011001 #
b10110100 "
#1035
b10110110 "
b10010111 #
#1045
b10010110 #
b10111001 "
#1055
b10111100 "
b10010100 #
#1065
b10010010 #
b10111110 "
#1075
b11000001 "
b10010001 #
#1085
b10001111 #
b11000100 "
#1095
b11000110 "
b10001110 #
#1105
b10001100 #
b11001001 "
#1115
b11001100 "
b10001011 #
#1125
b10001010 #
b11001111 "
#1135
b11010010 "
b10001001 #
#1145
b10000111 #
b11010101 "
#1155
b11011000 "
b10000110 #
#1165
b11011011 "
#1175
b11011110 "
b10000101 #
#1185
b10000100 #
b11100001 "
#1195
b11100100 "
b10000011 #
#1205
b10000010 #
b11100111 "
#1215
b11101010 "
#1225
b11101101 "
b10000001 #
#1235
b11110000 "
#1245
b11110011 "
#1255
b11110111 "
b10000000 #
#1265
b11111010 "
#1275
b11111101 "
#1285
b0 "
#1295
b11 "
#1305
b110 "
#1315
b1001 "
#1325
b1101 "
b10000001 #
#1335
b10000 "
#1345
b10011 "
#1355
b10110 "
b10000010 #
#1365
b11001 "
#1375
b11100 "
b10000011 #
#1385
b10000100 #
b11111 "
#1395
b100010 "
b10000101 #
#1405
b10000110 #
b100101 "
#1415
b101000 "
#1425
b101011 "
b10000111 #
#1435
b10001001 #
b101110 "
#1445
b110001 "
b10001010 #
#1455
b10001011 #
b110100 "
#1465
b110111 "
b10001100 #
#1475
b10001110 #
b111010 "
#1485
b111100 "
b10001111 #
#1495
b10010001 #
b111111 "
#1505
b1000010 "
b10010010 #
#1515
b10010100 #
b1000100 "
#1525
b1000111 "
b10010110 #
#1535
b10010111 #
b1001010 "
#1545
b1001100 "
b10011001 #
#1555
b10011011 #
b1001111 "
#1565
b1010001 "
b10011101 #
#1575
b10011111 #
b1010100 "
#1585
b1010110 "
b10100001 #
#1595
b10100011 #
b1011000 "
#1605
b1011011 "
b10100101 #
#1615
b10101000 #
b1011101 "
#1625
b1011111 "
b10101010 #
#1635
b10101100 #
b1100001 "
#1645
b1100011 "
b10101111 #
#1655
b10110001 #
b1100101 "
#1665
b1100111 "
b10110100 #
#1675
b10110110 #
b1101001 "
#1685
b1101010 "
b10111001 #
#1695
b10111100 #
b1101100 "
#1705
b1101110 "
b10111110 #
#1715
b11000001 #
b1101111 "
#1725
b1110001 "
b11000100 #
#1735
b11000110 #
b1110010 "
#1745
b1110100 "
b11001001 #
#1755
b11001100 #
b1110101 "
#1765
b1110110 "
b11001111 #
#1775
b11010010 #
b1110111 "
#1785
b1111001 "
b11010101 #
#1795
b11011000 #
b1111010 "
#1805
b11011011 #
#1815
b11011110 #
b1111011 "
#1825
b1111100 "
b11100001 #
#1835
b11100100 #
b1111101 "
#1845
b1111110 "
b11100111 #
#1855
b11101010 #
#1865
b11101101 #
b1111111 "
#1875
b11110000 #
#1885
b11110011 #
#1895
b11110111 #
#1905
b11111010 #
#1915
b11111101 #
#1925
b0 #
#1935
b11 #
#1945
b110 #
#1955
b1001 #
#1965
b1101 #
#1975
b10000 #
#1985
b10011 #
#1995
b10110 #
b1111110 "
#2005
b11001 #
#2015
b11100 #
b1111101 "
#2025
b1111100 "
b11111 #
#2035
b100010 #
b1111011 "
#2045
b1111010 "
b100101 #
#2055
b101000 #
#2065
b101011 #
b1111001 "
#2075
b1110111 "
b101110 #
#2085
b110001 #
b1110110 "
#2095
b1110101 "
b110100 #
#2105
b110111 #
b1110100 "
#2115
b1110010 "
b111010 #
#2125
b111100 #
b1110001 "
#2135
b1101111 "
b111111 #
#2145
b1000010 #
b1101110 "
#2155
b1101100 "
b1000100 #
#2165
b1000111 #
b1101010 "
#2175
b1101001 "
b1001010 #
#2185
b1001100 #
b1100111 "
#2195
b1100101 "
b1001111 #
#2205
b1010001 #
b1100011 "
#2215
b1100001 "
b1010100 #
#2225
b1010110 #
b1011111 "
#2235
b1011101 "
b1011000 #
#2245
b1011011 #
b1011011 "
#2255
b1011000 "
b1011101 #
#2265
b1011111 #
b1010110 "
#2275
b1010100 "
b1100001 #
#2285
b1100011 #
b1010001 "
#2295
b1001111 "
b1100101 #
#2305
b1100111 #
b1001100 "
#2315
b1001010 "
b1101001 #
#2325
b1101010 #
b1000111 "
#2335
b1000100 "
b1101100 #
#2345
b1101110 #
b1000010 "
#2355
b111111 "
b1101111 #
#2365
b1110001 #
b111100 "
#2375
b111010 "
b1110010 #
#2385
b1110100 #
b110111 "
#2395
b110100 "
b1110101 #
#2405
b1110110 #
b110001 "
#2415
b101110 "
b1110111 #
#2425
b1111001 #
b101011 "
#2435
b101000 "
b1111010 #
#2445
b100101 "
#2455
b100010 "
b1111011 #
#2465
b1111100 #
b11111 "
#2475
b11100 "
b1111101 #
#2485
b1111110 #
b11001 "
#2495
b10110 "
#2505
b10011 "
b1111111 #
#2515
b10000 "
#2525
b1101 "
#2535
b1001 "
#2545
b110 "
#2555
b11 "
#2565
b0 "
#2575
b11111101 "
#2585
b11111010 "
#2595
b11110111 "
#2605
b11110011 "
#2615
b11110000 "
#2625
b11101101 "
#2635
b11101010 "
b1111110 #
#2645
b11100111 "
#2655
b11100100 "
b1111101 #
#2665
b1111100 #
b11100001 "
#2675
b11011110 "
b1111011 #
#2685
b1111010 #
b11011011 "
#2695
b11011000 "
#2705
b11010101 "
b1111001 #
#2715
b1110111 #
b11010010 "
#2725
b11001111 "
b1110110 #
#2735
b1110101 #
b11001100 "
#2745
b11001001 "
b1110100 #
#2755
b1110010 #
b11000110 "
#2765
b11000100 "
b1110001 #
#2775
b1101111 #
b11000001 "
#2785
b10111110 "
b1101110 #
#2795
b1101100 #
b10111100 "
#2805
b10111001 "
b1101010 #
#2815
b1101001 #
b10110110 "
#2825
b10110100 "
b1100111 #
#2835
b1100101 #
b10110001 "
#2845
b10101111 "
b1100011 #
#2855
b1100001 #
b10101100 "
#2865
b10101010 "
b1011111 #
#2875
b1011101 #
b10101000 "
#2885
b10100101 "
b1011011 #
#2895
b1011000 #
b10100011 "
#2905
b10100001 "
b1010110 #
#2915
b1010100 #
b10011111 "
#2925
b10011101 "
b1010001 #
#2935
b1001111 #
b10011011 "
#2945
b10011001 "
b1001100 #
#2955
b1001010 #
b10010111 "
#2965
b10010110 "
b1000111 #
#2975
b1000100 #
b10010100 "
#2985
b10010010 "
b1000010 #
#2995
b111111 #
b10010001 "
#3005
b10001111 "
b111100 #
#3015
b111010 #
b10001110 "
#3025
b10001100 "
b110111 #
#3035
b110100 #
b10001011 "
#3045
b10001010 "
b110001 #
#3055
b101110 #
b10001001 "
#3065
b10000111 "
b101011 #
#3075
b101000 #
b10000110 "
#3085
b100101 #
#3095
b100010 #
b10000101 "
#3105
b10000100 "
b11111 #
#3115
b11100 #
b10000011 "
#3125
b10000010 "
b11001 #
#3135
b10110 #
#3145
b10011 #
b10000001 "
#3155
b10000 #
#3165
b1101 #
#3175
b1001 #
b10000000 "
#3185
b110 #
#3195
b11 #
#3205
b0 #
#3215
b11111101 #
#3225
b11111010 #
#3235
b11110111 #
#3245
b11110011 #
b10000001 "
#3255
b11110000 #
#3265
b11101101 #
#3275
b11101010 #
b10000010 "
#3285
b11100111 #
#3295
b11100100 #
b10000011 "
#3305
b10000100 "
b11100001 #
#3315
b11011110 #
b10000101 "
#3325
b10000110 "
b11011011 #
#3335
b11011000 #
#3345
b11010101 #
b10000111 "
#3355
b10001001 "
b11010010 #
#3365
b11001111 #
b10001010 "
#3375
b10001011 "
b11001100 #
#3385
b11001001 #
b10001100 "
#3395
b10001110 "
b11000110 #
#3405
b11000100 #
b10001111 "
#3415
b10010001 "
b11000001 #
#3425
b10111110 #
b10010010 "
#3435
b10010100 "
b10111100 #
#3445
b10111001 #
b10010110 "
#3455
b10010111 "
b10110110 #
#3465
b10110100 #
b10011001 "
#3475
b10011011 "
b10110001 #
#3485
b10101111 #
b10011101 "
#3495
b10011111 "
b10101100 #
#3505
b10101010 #
b10100001 "
#3515
b10100011 "
b10101000 #
#3525
b10100101 #
b10100101 "
#3535
b10101000 "
b10100011 #
#3545
b10100001 #
b10101010 "
#3555
b10101100 "
b10011111 #
#3565
b10011101 #
b10101111 "
#3575
b10110001 "
b10011011 #
#3585
b10011001 #
b10110100 "
#3595
b10110110 "
b10010111 #
#3605
b10010110 #
b10111001 "
#3615
b10111100 "
b10010100 #
#3625
b10010010 #
b10111110 "
#3635
b11000001 "
b10010001 #
#3645
b10001111 #
b11000100 "
#3655
b11000110 "
b10001110 #
#3665
b10001100 #
b11001001 "
#3675
b11001100 "
b10001011 #
#3685
b10001010 #
b11001111 "
#3695
b11010010 "
b10001001 #
#3705
b10000111 #
b11010101 "
#3715
b11011000 "
b10000110 #
#3725
b11011011 "
#3735
b11011110 "
b10000101 #
#3745
b10000100 #
b11100001 "
#3755
b11100100 "
b10000011 #
#3765
b10000010 #
b11100111 "
#3775
b11101010 "
#3785
b11101101 "
b10000001 #
#3795
b11110000 "
#3805
b11110011 "
#3815
b11110111 "
b10000000 #
#3825
b11111010 "
#3835
b11111101 "
#3845
b0 "
#3855
b11 "
#3865
b110 "
#3875
b1001 "
#3885
b1101 "
b10000001 #
#3895
b10000 "
#3905
b10011 "
#3915
b10110 "
b10000010 #
#3925
b11001 "
#3935
b11100 "
b10000011 #
#3945
b10000100 #
b11111 "
#3955
b100010 "
b10000101 #
#3965
b10000110 #
b100101 "
#3975
b101000 "
#3985
b101011 "
b10000111 #
#3995
b10001001 #
b101110 "
#4005
b110001 "
b10001010 #
#4015
b10001011 #
b110100 "
#4025
b110111 "
b10001100 #
#4035
b10001110 #
b111010 "
#4045
b111100 "
b10001111 #
#4055
b10010001 #
b111111 "
#4065
b1000010 "
b10010010 #
#4075
b10010100 #
b1000100 "
#4085
b1000111 "
b10010110 #
#4095
b10010111 #
b1001010 "
#4105
b1001100 "
b10011001 #
#4115
b10011011 #
b1001111 "
#4125
b1010001 "
b10011101 #
#4135
b10011111 #
b1010100 "
#4145
b1010110 "
b10100001 #
#4155
b10100011 #
b1011000 "
#4165
b1011011 "
b10100101 #
#4175
b10101000 #
b1011101 "
#4185
b1011111 "
b10101010 #
#4195
b10101100 #
b1100001 "
#4205
b1100011 "
b10101111 #
#4215
b10110001 #
b1100101 "
#4225
b1100111 "
b10110100 #
#4235
b10110110 #
b1101001 "
#4245
b1101010 "
b10111001 #
#4255
b10111100 #
b1101100 "
#4265
b1101110 "
b10111110 #
#4275
b11000001 #
b1101111 "
#4285
b1110001 "
b11000100 #
#4295
b11000110 #
b1110010 "
#4305
b1110100 "
b11001001 #
#4315
b11001100 #
b1110101 "
#4325
b1110110 "
b11001111 #
#4335
b11010010 #
b1110111 "
#4345
b1111001 "
b11010101 #
#4355
b11011000 #
b1111010 "
#4365
b11011011 #
#4375
b11011110 #
b1111011 "
#4385
b1111100 "
b11100001 #
#4395
b11100100 #
b1111101 "
#4405
b1111110 "
b11100111 #
#4415
b11101010 #
#4425
b11101101 #
b1111111 "
#4435
b11110000 #
#4445
b11110011 #
#4455
b11110111 #
#4465
b11111010 #
#4475
b11111101 #
#4485
b0 #
#4495
b11 #
#4505
b110 #
#4515
b1001 #
#4525
b1101 #
#4535
b10000 #
#4545
b10011 #
#4555
b10110 #
b1111110 "
#4565
b11001 #
#4575
b11100 #
b1111101 "
#4585
b1111100 "
b11111 #
#4595
b100010 #
b1111011 "
#4605
b1111010 "
b100101 #
#4615
b101000 #
#4625
b101011 #
b1111001 "
#4635
b1110111 "
b101110 #
#4645
b110001 #
b1110110 "
#4655
b1110101 "
b110100 #
#4665
b110111 #
b1110100 "
#4675
b1110010 "
b111010 #
#4685
b111100 #
b1110001 "
#4695
b1101111 "
b111111 #
#4705
b1000010 #
b1101110 "
#4715
b1101100 "
b1000100 #
#4725
b1000111 #
b1101010 "
#4735
b1101001 "
b1001010 #
#4745
b1001100 #
b1100111 "
#4755
b1100101 "
b1001111 #
#4765
b1010001 #
b1100011 "
#4775
b1100001 "
b1010100 #
#4785
b1010110 #
b1011111 "
#4795
b1011101 "
b1011000 #
#4805
b1011011 #
b1011011 "
#4815
b1011000 "
b1011101 #
#4825
b1011111 #
b1010110 "
#4835
b1010100 "
b1100001 #
#4845
b1100011 #
b1010001 "
#4855
b1001111 "
b1100101 #
#4865
b1100111 #
b1001100 "
#4875
b1001010 "
b1101001 #
#4885
b1101010 #
b1000111 "
#4895
b1000100 "
b1101100 #
#4905
b1101110 #
b1000010 "
#4915
b111111 "
b1101111 #
