EECS 598/Task4_LUT.v
module Cosine_LUT (
    input [7:0] phase,
    output reg signed [7:0] cosine_value
);

    always @(*) begin 
        case (phase)
            8'd0: cosine_value = 8'b01111111;
            8'd1: cosine_value = 8'b01111111;
            8'd2: cosine_value = 8'b01111111;
            8'd3: cosine_value = 8'b01111111;
            8'd4: cosine_value = 8'b01111111;
            8'd5: cosine_value = 8'b01111111;
            8'd6: cosine_value = 8'b01111111;
            8'd7: cosine_value = 8'b01111110;
            8'd8: cosine_value = 8'b01111110;
            8'd9: cosine_value = 8'b01111101;
            8'd10: cosine_value = 8'b01111100;
            8'd11: cosine_value = 8'b01111011;
            8'd12: cosine_value = 8'b01111010;
            8'd13: cosine_value = 8'b01111010;
            8'd14: cosine_value = 8'b01111001;
            8'd15: cosine_value = 8'b01110111;
            8'd16: cosine_value = 8'b01110110;
            8'd17: cosine_value = 8'b01110101;
            8'd18: cosine_value = 8'b01110100;
            8'd19: cosine_value = 8'b01110010;
            8'd20: cosine_value = 8'b01110001;
            8'd21: cosine_value = 8'b01101111;
            8'd22: cosine_value = 8'b01101110;
            8'd23: cosine_value = 8'b01101100;
            8'd24: cosine_value = 8'b01101010;
            8'd25: cosine_value = 8'b01101001;
            8'd26: cosine_value = 8'b01100111;
            8'd27: cosine_value = 8'b01100101;
            8'd28: cosine_value = 8'b01100011;
            8'd29: cosine_value = 8'b01100001;
            8'd30: cosine_value = 8'b01011111;
            8'd31: cosine_value = 8'b01011101;
            8'd32: cosine_value = 8'b01011011;
            8'd33: cosine_value = 8'b01011000;
            8'd34: cosine_value = 8'b01010110;
            8'd35: cosine_value = 8'b01010100;
            8'd36: cosine_value = 8'b01010001;
            8'd37: cosine_value = 8'b01001111;
            8'd38: cosine_value = 8'b01001100;
            8'd39: cosine_value = 8'b01001010;
            8'd40: cosine_value = 8'b01000111;
            8'd41: cosine_value = 8'b01000100;
            8'd42: cosine_value = 8'b01000010;
            8'd43: cosine_value = 8'b00111111;
            8'd44: cosine_value = 8'b00111100;
            8'd45: cosine_value = 8'b00111010;
            8'd46: cosine_value = 8'b00110111;
            8'd47: cosine_value = 8'b00110100;
            8'd48: cosine_value = 8'b00110001;
            8'd49: cosine_value = 8'b00101110;
            8'd50: cosine_value = 8'b00101011;
            8'd51: cosine_value = 8'b00101000;
            8'd52: cosine_value = 8'b00100101;
            8'd53: cosine_value = 8'b00100010;
            8'd54: cosine_value = 8'b00011111;
            8'd55: cosine_value = 8'b00011100;
            8'd56: cosine_value = 8'b00011001;
            8'd57: cosine_value = 8'b00010110;
            8'd58: cosine_value = 8'b00010011;
            8'd59: cosine_value = 8'b00010000;
            8'd60: cosine_value = 8'b00001101;
            8'd61: cosine_value = 8'b00001001;
            8'd62: cosine_value = 8'b00000110;
            8'd63: cosine_value = 8'b00000011;
            8'd64: cosine_value = 8'b00000000;
            8'd65: cosine_value = 8'b11111101;
            8'd66: cosine_value = 8'b11111010;
            8'd67: cosine_value = 8'b11110111;
            8'd68: cosine_value = 8'b11110011;
            8'd69: cosine_value = 8'b11110000;
            8'd70: cosine_value = 8'b11101101;
            8'd71: cosine_value = 8'b11101010;
            8'd72: cosine_value = 8'b11100111;
            8'd73: cosine_value = 8'b11100100;
            8'd74: cosine_value = 8'b11100001;
            8'd75: cosine_value = 8'b11011110;
            8'd76: cosine_value = 8'b11011011;
            8'd77: cosine_value = 8'b11011000;
            8'd78: cosine_value = 8'b11010101;
            8'd79: cosine_value = 8'b11010010;
            8'd80: cosine_value = 8'b11001111;
            8'd81: cosine_value = 8'b11001100;
            8'd82: cosine_value = 8'b11001001;
            8'd83: cosine_value = 8'b11000110;
            8'd84: cosine_value = 8'b11000100;
            8'd85: cosine_value = 8'b11000001;
            8'd86: cosine_value = 8'b10111110;
            8'd87: cosine_value = 8'b10111100;
            8'd88: cosine_value = 8'b10111001;
            8'd89: cosine_value = 8'b10110110;
            8'd90: cosine_value = 8'b10110100;
            8'd91: cosine_value = 8'b10110001;
            8'd92: cosine_value = 8'b10101111;
            8'd93: cosine_value = 8'b10101100;
            8'd94: cosine_value = 8'b10101010;
            8'd95: cosine_value = 8'b10101000;
            8'd96: cosine_value = 8'b10100101;
            8'd97: cosine_value = 8'b10100011;
            8'd98: cosine_value = 8'b10100001;
            8'd99: cosine_value = 8'b10011111;
            8'd100: cosine_value = 8'b10011101;
            8'd101: cosine_value = 8'b10011011;
            8'd102: cosine_value = 8'b10011001;
            8'd103: cosine_value = 8'b10010111;
            8'd104: cosine_value = 8'b10010110;
            8'd105: cosine_value = 8'b10010100;
            8'd106: cosine_value = 8'b10010010;
            8'd107: cosine_value = 8'b10010001;
            8'd108: cosine_value = 8'b10001111;
            8'd109: cosine_value = 8'b10001110;
            8'd110: cosine_value = 8'b10001100;
            8'd111: cosine_value = 8'b10001011;
            8'd112: cosine_value = 8'b10001010;
            8'd113: cosine_value = 8'b10001001;
            8'd114: cosine_value = 8'b10000111;
            8'd115: cosine_value = 8'b10000110;
            8'd116: cosine_value = 8'b10000110;
            8'd117: cosine_value = 8'b10000101;
            8'd118: cosine_value = 8'b10000100;
            8'd119: cosine_value = 8'b10000011;
            8'd120: cosine_value = 8'b10000010;
            8'd121: cosine_value = 8'b10000010;
            8'd122: cosine_value = 8'b10000001;
            8'd123: cosine_value = 8'b10000001;
            8'd124: cosine_value = 8'b10000001;
            8'd125: cosine_value = 8'b10000000;
            8'd126: cosine_value = 8'b10000000;
            8'd127: cosine_value = 8'b10000000;
            8'd128: cosine_value = 8'b10000000;
            8'd129: cosine_value = 8'b10000000;
            8'd130: cosine_value = 8'b10000000;
            8'd131: cosine_value = 8'b10000000;
            8'd132: cosine_value = 8'b10000001;
            8'd133: cosine_value = 8'b10000001;
            8'd134: cosine_value = 8'b10000001;
            8'd135: cosine_value = 8'b10000010;
            8'd136: cosine_value = 8'b10000010;
            8'd137: cosine_value = 8'b10000011;
            8'd138: cosine_value = 8'b10000100;
            8'd139: cosine_value = 8'b10000101;
            8'd140: cosine_value = 8'b10000110;
            8'd141: cosine_value = 8'b10000110;
            8'd142: cosine_value = 8'b10000111;
            8'd143: cosine_value = 8'b10001001;
            8'd144: cosine_value = 8'b10001010;
            8'd145: cosine_value = 8'b10001011;
            8'd146: cosine_value = 8'b10001100;
            8'd147: cosine_value = 8'b10001110;
            8'd148: cosine_value = 8'b10001111;
            8'd149: cosine_value = 8'b10010001;
            8'd150: cosine_value = 8'b10010010;
            8'd151: cosine_value = 8'b10010100;
            8'd152: cosine_value = 8'b10010110;
            8'd153: cosine_value = 8'b10010111;
            8'd154: cosine_value = 8'b10011001;
            8'd155: cosine_value = 8'b10011011;
            8'd156: cosine_value = 8'b10011101;
            8'd157: cosine_value = 8'b10011111;
            8'd158: cosine_value = 8'b10100001;
            8'd159: cosine_value = 8'b10100011;
            8'd160: cosine_value = 8'b10100101;
            8'd161: cosine_value = 8'b10101000;
            8'd162: cosine_value = 8'b10101010;
            8'd163: cosine_value = 8'b10101100;
            8'd164: cosine_value = 8'b10101111;
            8'd165: cosine_value = 8'b10110001;
            8'd166: cosine_value = 8'b10110100;
            8'd167: cosine_value = 8'b10110110;
            8'd168: cosine_value = 8'b10111001;
            8'd169: cosine_value = 8'b10111100;
            8'd170: cosine_value = 8'b10111110;
            8'd171: cosine_value = 8'b11000001;
            8'd172: cosine_value = 8'b11000100;
            8'd173: cosine_value = 8'b11000110;
            8'd174: cosine_value = 8'b11001001;
            8'd175: cosine_value = 8'b11001100;
            8'd176: cosine_value = 8'b11001111;
            8'd177: cosine_value = 8'b11010010;
            8'd178: cosine_value = 8'b11010101;
            8'd179: cosine_value = 8'b11011000;
            8'd180: cosine_value = 8'b11011011;
            8'd181: cosine_value = 8'b11011110;
            8'd182: cosine_value = 8'b11100001;
            8'd183: cosine_value = 8'b11100100;
            8'd184: cosine_value = 8'b11100111;
            8'd185: cosine_value = 8'b11101010;
            8'd186: cosine_value = 8'b11101101;
            8'd187: cosine_value = 8'b11110000;
            8'd188: cosine_value = 8'b11110011;
            8'd189: cosine_value = 8'b11110111;
            8'd190: cosine_value = 8'b11111010;
            8'd191: cosine_value = 8'b11111101;
            8'd192: cosine_value = 8'b00000000;
            8'd193: cosine_value = 8'b00000011;
            8'd194: cosine_value = 8'b00000110;
            8'd195: cosine_value = 8'b00001001;
            8'd196: cosine_value = 8'b00001101;
            8'd197: cosine_value = 8'b00010000;
            8'd198: cosine_value = 8'b00010011;
            8'd199: cosine_value = 8'b00010110;
            8'd200: cosine_value = 8'b00011001;
            8'd201: cosine_value = 8'b00011100;
            8'd202: cosine_value = 8'b00011111;
            8'd203: cosine_value = 8'b00100010;
            8'd204: cosine_value = 8'b00100101;
            8'd205: cosine_value = 8'b00101000;
            8'd206: cosine_value = 8'b00101011;
            8'd207: cosine_value = 8'b00101110;
            8'd208: cosine_value = 8'b00110001;
            8'd209: cosine_value = 8'b00110100;
            8'd210: cosine_value = 8'b00110111;
            8'd211: cosine_value = 8'b00111010;
            8'd212: cosine_value = 8'b00111100;
            8'd213: cosine_value = 8'b00111111;
            8'd214: cosine_value = 8'b01000010;
            8'd215: cosine_value = 8'b01000100;
            8'd216: cosine_value = 8'b01000111;
            8'd217: cosine_value = 8'b01001010;
            8'd218: cosine_value = 8'b01001100;
            8'd219: cosine_value = 8'b01001111;
            8'd220: cosine_value = 8'b01010001;
            8'd221: cosine_value = 8'b01010100;
            8'd222: cosine_value = 8'b01010110;
            8'd223: cosine_value = 8'b01011000;
            8'd224: cosine_value = 8'b01011011;
            8'd225: cosine_value = 8'b01011101;
            8'd226: cosine_value = 8'b01011111;
            8'd227: cosine_value = 8'b01100001;
            8'd228: cosine_value = 8'b01100011;
            8'd229: cosine_value = 8'b01100101;
            8'd230: cosine_value = 8'b01100111;
            8'd231: cosine_value = 8'b01101001;
            8'd232: cosine_value = 8'b01101010;
            8'd233: cosine_value = 8'b01101100;
            8'd234: cosine_value = 8'b01101110;
            8'd235: cosine_value = 8'b01101111;
            8'd236: cosine_value = 8'b01110001;
            8'd237: cosine_value = 8'b01110010;
            8'd238: cosine_value = 8'b01110100;
            8'd239: cosine_value = 8'b01110101;
            8'd240: cosine_value = 8'b01110110;
            8'd241: cosine_value = 8'b01110111;
            8'd242: cosine_value = 8'b01111001;
            8'd243: cosine_value = 8'b01111010;
            8'd244: cosine_value = 8'b01111010;
            8'd245: cosine_value = 8'b01111011;
            8'd246: cosine_value = 8'b01111100;
            8'd247: cosine_value = 8'b01111101;
            8'd248: cosine_value = 8'b01111110;
            8'd249: cosine_value = 8'b01111110;
            8'd250: cosine_value = 8'b01111111;
            8'd251: cosine_value = 8'b01111111;
            8'd252: cosine_value = 8'b01111111;
            8'd253: cosine_value = 8'b01111111;
            8'd254: cosine_value = 8'b01111111;
            8'd255: cosine_value = 8'b01111111;
            default: cosine_value = 8'd0;
        endcase
    end
endmodule



module my_waveform_gem (
    input clk,
    input reset,
    input signed [8:0] control,
    output [7:0] my_sine_out,
    output [7:0] my_cosine_out
);

    reg signed [8:0] phase_change;
    

    always @(posedge clk) begin
        if (reset) 
            phase_change <= 9'sd0;
        else
            phase_change <= phase_change + control;
    end

    // Instantiation for cosine LUT output
    wire [7:0] lut_entry = phase_change [7:0];

    Cosine_LUT cos_ut (
        .phase(lut_entry),
        .cosine_value(my_cosine_out)
    );

    // Instantiation for sine LUT output
    Cosine_LUT sin_ut (
        .phase(lut_entry + 8'd64),  // 90-degree phase shift equivalent in terms of entry number
        .cosine_value(my_sine_out)
    );


endmodule


module my_controller (
    input clk, 
    input reset,
    input [7:0] period,
    output reg signed [8:0] control
);


    reg [13:0] counter;
    reg [13:0] half_period; // The number of the clock cycles
    reg signed [8:0] control_hf;
    reg signed [8:0] control_lf;
    reg switch; // Help to make switch between the two frequency


    // Initialize the control signal for each frequency (high for hf and low for lf)
    initial begin
        control_hf = 9'sd6;
        control_lf = 9'sd1;

    end


    // Alternates the frequency between 2.3 MHz and 0.3 MHz with the input period
    // reset cases - reset and period change
    always @(posedge clk) begin
        if (reset) begin
            counter <= 14'd0;
            switch <= 1'b0;
            control <= control_hf;
            half_period <= period * 8'd50;
        end else begin
        // Alternate the frequency when counter reaches the number of cycles for each half period
        if (counter >= half_period - 1) begin
            counter <= 14'd0;
            switch <= ~switch;
            control <= (~switch) ? control_lf : control_hf;
        end else begin
            counter <= counter + 14'd1;
        end
        // $display("counter number is:\t", counter);
        // $display("switch is:\t", switch);
        end
    end

endmodule

EECS 598/Task4b_tb.v
`timescale 1ns/1ns
module my_waveform_gem_tb;


    reg clk;
    reg reset;
    reg [7:0] period;
    wire signed [8:0] control;
    wire [7:0] my_sine_out;
    wire [7:0] my_cosine_out;
    integer outfile;


    // The instantiation of my waveform generator
    my_waveform_gem uut1 (
        .clk(clk),
        .reset(reset),
        .control(control),
        .my_sine_out(my_sine_out),
        .my_cosine_out(my_cosine_out)
    );

    my_controller uut2 (
        .clk(clk),
        .reset(reset),
        .period(period),
        .control(control)
    );

    // Create a file to store the sine and cosine outputs
    initial begin
        outfile = $fopen("output_data.txt", "w");
    end


    // 100 MHz clock - 10 ns clock period (clock cycle)
    initial clk = 0;
    always #5 clk = ~clk;

    initial begin
    // Dump the simulation result to a VCD file
        $dumpfile("waveform.vcd");
        $dumpvars(0, my_waveform_gem_tb);

        reset = 1;
        period = 8'd16;
        #10;
        reset = 0;
        
        #100000;

        // // Start test 1 - 3.29 MHz
        // control = 9'sd8;
        // #800;   // Roughly 2 time periods

        // // Start test 2 - -1.35 MHz
        // control = -9'sd3;
        // #2000;  // Roughly 2 time periods

        // // Start test 3 - 0.43 MHz
        // control = 9'sd1;
        // #5000; // Roughly 2 time periods

        $finish;

    end

    // Store the sine and cosine outputs to the file
    always @(posedge clk) begin
        if (!reset) begin
            $fwrite(outfile, "%d, %d\n", my_sine_out, my_cosine_out);
        end
    end



    endmodule

EECS 598/controller.vcd
$date
	Sat Sep 21 21:37:38 2024
$end
$version
	GTKWave Analyzer v3.3.100 (w)1999-2019 BSI
$end
$timescale
	1ns
$end
$scope module my_waveform_gem_tb $end
$var wire 8 # my_cosine_out[7:0] $end
$var wire 8 " my_sine_out[7:0] $end
$upscope $end
$enddefinitions $end
$dumpvars
#0
bx "
bx #
#5
b1111111 #
b0 "
#15
b11101101 "
#25
b11011011 "
b1111010 #
#35
b1110100 #
b11001001 "
#45
b10111001 "
b1101010 #
#55
b1011111 #
b10101010 "
#65
b10011101 "
b1010001 #
#75
b1000010 #
b10010010 "
#85
b10001010 "
b110001 #
#95
b11111 #
b10000100 "
#105
b10000001 "
b1101 #
#115
b11111010 #
b10000000 "
#125
b10000010 "
b11100111 #
#135
b11010101 #
b10000111 "
#145
b10001111 "
b11000100 #
#155
b10110100 #
b10011001 "
#165
b10100101 "
b10100101 #
#175
b10011001 #
b10110100 "
#185
b11000100 "
b10001111 #
#195
b10000111 #
b11010101 "
#205
b11100111 "
b10000010 #
#215
b10000000 #
b11111010 "
#225
b1101 "
b10000001 #
#235
b10000100 #
b11111 "
#245
b110001 "
b10001010 #
#255
b10010010 #
b1000010 "
#265
b1010001 "
b10011101 #
#275
b10101010 #
b1011111 "
#285
b1101010 "
b10111001 #
#295
b11001001 #
b1110100 "
#305
b1111010 "
b11011011 #
#315
b11101101 #
b1111111 "
#325
b0 #
#335
b10011 #
#345
b100101 #
b1111010 "
#355
b1110100 "
b110111 #
#365
b1000111 #
b1101010 "
#375
b1011111 "
b1010110 #
#385
b1100011 #
b1010001 "
#395
b1000010 "
b1101110 #
#405
b1110110 #
b110001 "
#415
b11111 "
b1111100 #
#425
b1111111 #
b1101 "
#435
b11111010 "
#445
b11100111 "
b1111110 #
#455
b1111001 #
b11010101 "
#465
b11000100 "
b1110001 #
#475
b1100111 #
b10110100 "
#485
b10100101 "
b1011011 #
#495
b1001100 #
b10011001 "
#505
b10001111 "
b111100 #
#515
b101011 #
b10000111 "
#525
b10000010 "
b11001 #
#535
b110 #
b10000000 "
#545
b10000001 "
b11110011 #
#555
b11100001 #
b10000100 "
#565
b10001010 "
b11001111 #
#575
b10111110 #
b10010010 "
#585
b10011101 "
b10101111 #
#595
b10100001 #
b10101010 "
#605
b10111001 "
b10010110 #
#615
b10001100 #
b11001001 "
#625
b11011011 "
b10000110 #
#635
b10000001 #
b11101101 "
#645
b0 "
b10000000 #
#655
b10000001 #
b10011 "
#665
b100101 "
b10000110 #
#675
b10001100 #
b110111 "
#685
b1000111 "
b10010110 #
#695
b10100001 #
b1010110 "
#705
b1100011 "
b10101111 #
#715
b10111110 #
b1101110 "
#725
b1110110 "
b11001111 #
#735
b11100001 #
b1111100 "
#745
b1111111 "
b11110011 #
#755
b110 #
#765
b11001 #
b1111110 "
#775
b1111001 "
b101011 #
#785
b111100 #
b1110001 "
#795
b1100111 "
b1001100 #
#805
b1011011 #
b1011011 "
#815
b1001100 "
b1100111 #
#825
b1110001 #
b111100 "
#835
b101011 "
b1111001 #
#845
b1111110 #
b11001 "
#855
b110 "
b1111111 #
#865
b11110011 "
#875
b11100001 "
b1111100 #
#885
b1110110 #
b11001111 "
#895
b10111110 "
b1101110 #
#905
b1100011 #
b10101111 "
#915
b10100001 "
b1010110 #
#925
b1000111 #
b10010110 "
#935
b10001100 "
b110111 #
#945
b100101 #
b10000110 "
#955
b10000001 "
b10011 #
#965
b0 #
b10000000 "
#975
b10000001 "
b11101101 #
#985
b11011011 #
b10000110 "
#995
b10001100 "
b11001001 #
#1005
b10111001 #
b10010110 "
#1015
b10100001 "
b10101010 #
#1025
b10011101 #
b10101111 "
#1035
b10111110 "
b10010010 #
#1045
b10001010 #
b11001111 "
#1055
b11100001 "
b10000100 #
#1065
b10000001 #
b11110011 "
#1075
b110 "
b10000000 #
#1085
b10000010 #
b11001 "
#1095
b101011 "
b10000111 #
#1105
b10001111 #
b111100 "
#1115
b1001100 "
b10011001 #
#1125
b10100101 #
b1011011 "
#1135
b1100111 "
b10110100 #
#1145
b11000100 #
b1110001 "
#1155
b1111001 "
b11010101 #
#1165
b11100111 #
b1111110 "
#1175
b1111111 "
b11111010 #
#1185
b1101 #
#1195
b11111 #
b1111100 "
#1205
b1110110 "
b110001 #
#1215
b1000010 #
b1101110 "
#1225
b1100011 "
b1010001 #
#1235
b1011111 #
b1010110 "
#1245
b1000111 "
b1101010 #
#1255
b1110100 #
b110111 "
#1265
b100101 "
b1111010 #
#1275
b1111111 #
b10011 "
#1285
b0 "
#1295
b11101101 "
#1305
b11011011 "
b1111010 #
#1315
b1110100 #
b11001001 "
#1325
b10111001 "
b1101010 #
#1335
b1011111 #
b10101010 "
#1345
b10011101 "
b1010001 #
#1355
b1000010 #
b10010010 "
#1365
b10001010 "
b110001 #
#1375
b11111 #
b10000100 "
#1385
b10000001 "
b1101 #
#1395
b11111010 #
b10000000 "
#1405
b10000010 "
b11100111 #
#1415
b11010101 #
b10000111 "
#1425
b10001111 "
b11000100 #
#1435
b10110100 #
b10011001 "
#1445
b10100101 "
b10100101 #
#1455
b10011001 #
b10110100 "
#1465
b11000100 "
b10001111 #
#1475
b10000111 #
b11010101 "
#1485
b11100111 "
b10000010 #
#1495
b10000000 #
b11111010 "
#1505
b1101 "
b10000001 #
#1515
b10000100 #
b11111 "
#1525
b110001 "
b10001010 #
#1535
b10010010 #
b1000010 "
#1545
b1010001 "
b10011101 #
#1555
b10101010 #
b1011111 "
#1565
b1101010 "
b10111001 #
#1575
b11001001 #
b1110100 "
#1585
b1111010 "
b11011011 #
#1595
b11101101 #
b1111111 "
#1605
b0 #
#1615
b10011 #
#1625
b100101 #
b1111010 "
#1635
b1110100 "
b110111 #
#1645
b1000111 #
b1101010 "
#1655
b1011111 "
b1010110 #
#1665
b1100011 #
b1010001 "
#1675
b1000010 "
b1101110 #
#1685
b1110110 #
b110001 "
#1695
b11111 "
b1111100 #
#1705
b1111111 #
b1101 "
#1715
b11111010 "
#1725
b11100111 "
b1111110 #
#1735
b1111001 #
b11010101 "
#1745
b11000100 "
b1110001 #
#1755
b1100111 #
b10110100 "
#1765
b10100101 "
b1011011 #
#1775
b1001100 #
b10011001 "
#1785
b10001111 "
b111100 #
#1795
b101011 #
b10000111 "
#1805
b10000010 "
b11001 #
#1815
b110 #
b10000000 "
#1825
b10000001 "
b11110011 #
#1835
b11100001 #
b10000100 "
#1845
b10001010 "
b11001111 #
#1855
b10111110 #
b10010010 "
#1865
b10011101 "
b10101111 #
#1875
b10100001 #
b10101010 "
#1885
b10111001 "
b10010110 #
#1895
b10001100 #
b11001001 "
#1905
b11011011 "
b10000110 #
#1915
b10000001 #
b11101101 "
#1925
b0 "
b10000000 #
#1935
b10000001 #
b10011 "
#1945
b100101 "
b10000110 #
#1955
b10001100 #
b110111 "
#1965
b1000111 "
b10010110 #
#1975
b10100001 #
b1010110 "
#1985
b1100011 "
b10101111 #
#1995
b10111110 #
b1101110 "
#2005
b1110110 "
b11001111 #
#2015
b11100001 #
b1111100 "
#2025
b1111111 "
b11110011 #
#2035
b110 #
#2045
b11001 #
b1111110 "
#2055
b1111001 "
b101011 #
#2065
b111100 #
b1110001 "
#2075
b1100111 "
b1001100 #
#2085
b1011011 #
b1011011 "
#2095
b1001100 "
b1100111 #
#2105
b1110001 #
b111100 "
#2115
b101011 "
b1111001 #
#2125
b1111110 #
b11001 "
#2135
b110 "
b1111111 #
#2145
b11110011 "
#2155
b11100001 "
b1111100 #
#2165
b1110110 #
b11001111 "
#2175
b10111110 "
b1101110 #
#2185
b1100011 #
b10101111 "
#2195
b10100001 "
b1010110 #
#2205
b1000111 #
b10010110 "
#2215
b10001100 "
b110111 #
#2225
b100101 #
b10000110 "
#2235
b10000001 "
b10011 #
#2245
b0 #
b10000000 "
#2255
b10000001 "
b11101101 #
#2265
b11011011 #
b10000110 "
#2275
b10001100 "
b11001001 #
#2285
b10111001 #
b10010110 "
#2295
b10100001 "
b10101010 #
#2305
b10011101 #
b10101111 "
#2315
b10111110 "
b10010010 #
#2325
b10001010 #
b11001111 "
#2335
b11100001 "
b10000100 #
#2345
b10000001 #
b11110011 "
#2355
b110 "
b10000000 #
#2365
b10000010 #
b11001 "
#2375
b101011 "
b10000111 #
#2385
b10001111 #
b111100 "
#2395
b1001100 "
b10011001 #
#2405
b10100101 #
b1011011 "
#2415
b1100111 "
b10110100 #
#2425
b11000100 #
b1110001 "
#2435
b1111001 "
b11010101 #
#2445
b11100111 #
b1111110 "
#2455
b1111111 "
b11111010 #
#2465
b1101 #
#2475
b11111 #
b1111100 "
#2485
b1110110 "
b110001 #
#2495
b1000010 #
b1101110 "
#2505
b1100011 "
b1010001 #
#2515
b1011111 #
b1010110 "
#2525
b1000111 "
b1101010 #
#2535
b1110100 #
b110111 "
#2545
b100101 "
b1111010 #
#2555
b1111111 #
b10011 "
#2565
b0 "
#2575
b11101101 "
#2585
b11011011 "
b1111010 #
#2595
b1110100 #
b11001001 "
#2605
b10111001 "
b1101010 #
#2615
b1011111 #
b10101010 "
#2625
b10011101 "
b1010001 #
#2635
b1000010 #
b10010010 "
#2645
b10001010 "
b110001 #
#2655
b11111 #
b10000100 "
#2665
b10000001 "
b1101 #
#2675
b11111010 #
b10000000 "
#2685
b10000010 "
b11100111 #
#2695
b11010101 #
b10000111 "
#2705
b10001111 "
b11000100 #
#2715
b10110100 #
b10011001 "
#2725
b10100101 "
b10100101 #
#2735
b10011001 #
b10110100 "
#2745
b11000100 "
b10001111 #
#2755
b10000111 #
b11010101 "
#2765
b11100111 "
b10000010 #
#2775
b10000000 #
b11111010 "
#2785
b1101 "
b10000001 #
#2795
b10000100 #
b11111 "
#2805
b110001 "
b10001010 #
#2815
b10010010 #
b1000010 "
#2825
b1010001 "
b10011101 #
#2835
b10101010 #
b1011111 "
#2845
b1101010 "
b10111001 #
#2855
b11001001 #
b1110100 "
#2865
b1111010 "
b11011011 #
#2875
b11101101 #
b1111111 "
#2885
b0 #
#2895
b10011 #
#2905
b100101 #
b1111010 "
#2915
b1110100 "
b110111 #
#2925
b1000111 #
b1101010 "
#2935
b1011111 "
b1010110 #
#2945
b1100011 #
b1010001 "
#2955
b1000010 "
b1101110 #
#2965
b1110110 #
b110001 "
#2975
b11111 "
b1111100 #
#2985
b1111111 #
b1101 "
#2995
b11111010 "
#3005
b11100111 "
b1111110 #
#3015
b1111001 #
b11010101 "
#3025
b11000100 "
b1110001 #
#3035
b1100111 #
b10110100 "
#3045
b10100101 "
b1011011 #
#3055
b1001100 #
b10011001 "
#3065
b10001111 "
b111100 #
#3075
b101011 #
b10000111 "
#3085
b10000010 "
b11001 #
#3095
b110 #
b10000000 "
#3105
b10000001 "
b11110011 #
#3115
b11100001 #
b10000100 "
#3125
b10001010 "
b11001111 #
#3135
b10111110 #
b10010010 "
#3145
b10011101 "
b10101111 #
#3155
b10100001 #
b10101010 "
#3165
b10111001 "
b10010110 #
#3175
b10001100 #
b11001001 "
#3185
b11011011 "
b10000110 #
#3195
b10000001 #
b11101101 "
#3205
b0 "
b10000000 #
#3215
b10000001 #
b10011 "
#3225
b100101 "
b10000110 #
#3235
b10001100 #
b110111 "
#3245
b1000111 "
b10010110 #
#3255
b10100001 #
b1010110 "
#3265
b1100011 "
b10101111 #
#3275
b10111110 #
b1101110 "
#3285
b1110110 "
b11001111 #
#3295
b11100001 #
b1111100 "
#3305
b1111111 "
b11110011 #
#3315
b110 #
#3325
b11001 #
b1111110 "
#3335
b1111001 "
b101011 #
#3345
b111100 #
b1110001 "
#3355
b1100111 "
b1001100 #
#3365
b1011011 #
b1011011 "
#3375
b1001100 "
b1100111 #
#3385
b1110001 #
b111100 "
#3395
b101011 "
b1111001 #
#3405
b1111110 #
b11001 "
#3415
b110 "
b1111111 #
#3425
b11110011 "
#3435
b11100001 "
b1111100 #
#3445
b1110110 #
b11001111 "
#3455
b10111110 "
b1101110 #
#3465
b1100011 #
b10101111 "
#3475
b10100001 "
b1010110 #
#3485
b1000111 #
b10010110 "
#3495
b10001100 "
b110111 #
#3505
b100101 #
b10000110 "
#3515
b10000001 "
b10011 #
#3525
b0 #
b10000000 "
#3535
b10000001 "
b11101101 #
#3545
b11011011 #
b10000110 "
#3555
b10001100 "
b11001001 #
#3565
b10111001 #
b10010110 "
#3575
b10100001 "
b10101010 #
#3585
b10011101 #
b10101111 "
#3595
b10111110 "
b10010010 #
#3605
b10001010 #
b11001111 "
#3615
b11100001 "
b10000100 #
#3625
b10000001 #
b11110011 "
#3635
b110 "
b10000000 #
#3645
b10000010 #
b11001 "
#3655
b101011 "
b10000111 #
#3665
b10001111 #
b111100 "
#3675
b1001100 "
b10011001 #
#3685
b10100101 #
b1011011 "
#3695
b1100111 "
b10110100 #
#3705
b11000100 #
b1110001 "
#3715
b1111001 "
b11010101 #
#3725
b11100111 #
b1111110 "
#3735
b1111111 "
b11111010 #
#3745
b1101 #
#3755
b11111 #
b1111100 "
#3765
b1110110 "
b110001 #
#3775
b1000010 #
b1101110 "
#3785
b1100011 "
b1010001 #
#3795
b1011111 #
b1010110 "
#3805
b1000111 "
b1101010 #
#3815
b1110100 #
b110111 "
#3825
b100101 "
b1111010 #
#3835
b1111111 #
b10011 "
#3845
b0 "
#3855
b11101101 "
#3865
b11011011 "
b1111010 #
#3875
b1110100 #
b11001001 "
#3885
b10111001 "
b1101010 #
#3895
b1011111 #
b10101010 "
#3905
b10011101 "
b1010001 #
#3915
b1000010 #
b10010010 "
#3925
b10001010 "
b110001 #
#3935
b11111 #
b10000100 "
#3945
b10000001 "
b1101 #
#3955
b11111010 #
b10000000 "
#3965
b10000010 "
b11100111 #
#3975
b11010101 #
b10000111 "
#3985
b10001111 "
b11000100 #
#3995
b10110100 #
b10011001 "
#4005
b10100101 "
b10100101 #
#4015
b10011001 #
b10110100 "
#4025
b11000100 "
b10001111 #
#4035
b10000111 #
b11010101 "
#4045
b11100111 "
b10000010 #
#4055
b10000000 #
b11111010 "
#4065
b1101 "
b10000001 #
#4075
b10000100 #
b11111 "
#4085
b110001 "
b10001010 #
#4095
b10010010 #
b1000010 "
#4105
b1010001 "
b10011101 #
#4115
b10101010 #
b1011111 "
#4125
b1101010 "
b10111001 #
#4135
b11001001 #
b1110100 "
#4145
b1111010 "
b11011011 #
#4155
b11101101 #
b1111111 "
#4165
b0 #
#4175
b10011 #
#4185
b100101 #
b1111010 "
#4195
b1110100 "
b110111 #
#4205
b1000111 #
b1101010 "
#4215
b1011111 "
b1010110 #
#4225
b1100011 #
b1010001 "
#4235
b1000010 "
b1101110 #
#4245
b1110110 #
b110001 "
#4255
b11111 "
b1111100 #
#4265
b1111111 #
b1101 "
#4275
b11111010 "
#4285
b11100111 "
b1111110 #
#4295
b1111001 #
b11010101 "
#4305
b11000100 "
b1110001 #
#4315
b1100111 #
b10110100 "
#4325
b10100101 "
b1011011 #
#4335
b1001100 #
b10011001 "
#4345
b10001111 "
b111100 #
#4355
b101011 #
b10000111 "
#4365
b10000010 "
b11001 #
#4375
b110 #
b10000000 "
#4385
b10000001 "
b11110011 #
#4395
b11100001 #
b10000100 "
#4405
b10001010 "
b11001111 #
#4415
b10111110 #
b10010010 "
#4425
b10011101 "
b10101111 #
#4435
b10100001 #
b10101010 "
#4445
b10111001 "
b10010110 #
#4455
b10001100 #
b11001001 "
#4465
b11011011 "
b10000110 #
#4475
b10000001 #
b11101101 "
#4485
b0 "
b10000000 #
#4495
b10000001 #
b10011 "
#4505
b100101 "
b10000110 #
#4515
b10001100 #
b110111 "
#4525
b1000111 "
b10010110 #
#4535
b10100001 #
b1010110 "
#4545
b1100011 "
b10101111 #
#4555
b10111110 #
b1101110 "
#4565
b1110110 "
b11001111 #
#4575
b11100001 #
b1111100 "
#4585
b1111111 "
b11110011 #
#4595
b110 #
#4605
b11001 #
b1111110 "
