EECS 598/Task4_LUT.v
module Cosine_LUT (
    input [7:0] phase,
    output reg signed [7:0] cosine_value
);

    always @(*) begin 
        case (phase)
            8'd0: cosine_value = 8'b01111111;
            8'd1: cosine_value = 8'b01111111;
            8'd2: cosine_value = 8'b01111111;
            8'd3: cosine_value = 8'b01111111;
            8'd4: cosine_value = 8'b01111111;
            8'd5: cosine_value = 8'b01111111;
            8'd6: cosine_value = 8'b01111111;
            8'd7: cosine_value = 8'b01111110;
            8'd8: cosine_value = 8'b01111110;
            8'd9: cosine_value = 8'b01111101;
            8'd10: cosine_value = 8'b01111100;
            8'd11: cosine_value = 8'b01111011;
            8'd12: cosine_value = 8'b01111010;
            8'd13: cosine_value = 8'b01111010;
            8'd14: cosine_value = 8'b01111001;
            8'd15: cosine_value = 8'b01110111;
            8'd16: cosine_value = 8'b01110110;
            8'd17: cosine_value = 8'b01110101;
            8'd18: cosine_value = 8'b01110100;
            8'd19: cosine_value = 8'b01110010;
            8'd20: cosine_value = 8'b01110001;
            8'd21: cosine_value = 8'b01101111;
            8'd22: cosine_value = 8'b01101110;
            8'd23: cosine_value = 8'b01101100;
            8'd24: cosine_value = 8'b01101010;
            8'd25: cosine_value = 8'b01101001;
            8'd26: cosine_value = 8'b01100111;
            8'd27: cosine_value = 8'b01100101;
            8'd28: cosine_value = 8'b01100011;
            8'd29: cosine_value = 8'b01100001;
            8'd30: cosine_value = 8'b01011111;
            8'd31: cosine_value = 8'b01011101;
            8'd32: cosine_value = 8'b01011011;
            8'd33: cosine_value = 8'b01011000;
            8'd34: cosine_value = 8'b01010110;
            8'd35: cosine_value = 8'b01010100;
            8'd36: cosine_value = 8'b01010001;
            8'd37: cosine_value = 8'b01001111;
            8'd38: cosine_value = 8'b01001100;
            8'd39: cosine_value = 8'b01001010;
            8'd40: cosine_value = 8'b01000111;
            8'd41: cosine_value = 8'b01000100;
            8'd42: cosine_value = 8'b01000010;
            8'd43: cosine_value = 8'b00111111;
            8'd44: cosine_value = 8'b00111100;
            8'd45: cosine_value = 8'b00111010;
            8'd46: cosine_value = 8'b00110111;
            8'd47: cosine_value = 8'b00110100;
            8'd48: cosine_value = 8'b00110001;
            8'd49: cosine_value = 8'b00101110;
            8'd50: cosine_value = 8'b00101011;
            8'd51: cosine_value = 8'b00101000;
            8'd52: cosine_value = 8'b00100101;
            8'd53: cosine_value = 8'b00100010;
            8'd54: cosine_value = 8'b00011111;
            8'd55: cosine_value = 8'b00011100;
            8'd56: cosine_value = 8'b00011001;
            8'd57: cosine_value = 8'b00010110;
            8'd58: cosine_value = 8'b00010011;
            8'd59: cosine_value = 8'b00010000;
            8'd60: cosine_value = 8'b00001101;
            8'd61: cosine_value = 8'b00001001;
            8'd62: cosine_value = 8'b00000110;
            8'd63: cosine_value = 8'b00000011;
            8'd64: cosine_value = 8'b00000000;
            8'd65: cosine_value = 8'b11111101;
            8'd66: cosine_value = 8'b11111010;
            8'd67: cosine_value = 8'b11110111;
            8'd68: cosine_value = 8'b11110011;
            8'd69: cosine_value = 8'b11110000;
            8'd70: cosine_value = 8'b11101101;
            8'd71: cosine_value = 8'b11101010;
            8'd72: cosine_value = 8'b11100111;
            8'd73: cosine_value = 8'b11100100;
            8'd74: cosine_value = 8'b11100001;
            8'd75: cosine_value = 8'b11011110;
            8'd76: cosine_value = 8'b11011011;
            8'd77: cosine_value = 8'b11011000;
            8'd78: cosine_value = 8'b11010101;
            8'd79: cosine_value = 8'b11010010;
            8'd80: cosine_value = 8'b11001111;
            8'd81: cosine_value = 8'b11001100;
            8'd82: cosine_value = 8'b11001001;
            8'd83: cosine_value = 8'b11000110;
            8'd84: cosine_value = 8'b11000100;
            8'd85: cosine_value = 8'b11000001;
            8'd86: cosine_value = 8'b10111110;
            8'd87: cosine_value = 8'b10111100;
            8'd88: cosine_value = 8'b10111001;
            8'd89: cosine_value = 8'b10110110;
            8'd90: cosine_value = 8'b10110100;
            8'd91: cosine_value = 8'b10110001;
            8'd92: cosine_value = 8'b10101111;
            8'd93: cosine_value = 8'b10101100;
            8'd94: cosine_value = 8'b10101010;
            8'd95: cosine_value = 8'b10101000;
            8'd96: cosine_value = 8'b10100101;
            8'd97: cosine_value = 8'b10100011;
            8'd98: cosine_value = 8'b10100001;
            8'd99: cosine_value = 8'b10011111;
            8'd100: cosine_value = 8'b10011101;
            8'd101: cosine_value = 8'b10011011;
            8'd102: cosine_value = 8'b10011001;
            8'd103: cosine_value = 8'b10010111;
            8'd104: cosine_value = 8'b10010110;
            8'd105: cosine_value = 8'b10010100;
            8'd106: cosine_value = 8'b10010010;
            8'd107: cosine_value = 8'b10010001;
            8'd108: cosine_value = 8'b10001111;
            8'd109: cosine_value = 8'b10001110;
            8'd110: cosine_value = 8'b10001100;
            8'd111: cosine_value = 8'b10001011;
            8'd112: cosine_value = 8'b10001010;
            8'd113: cosine_value = 8'b10001001;
            8'd114: cosine_value = 8'b10000111;
            8'd115: cosine_value = 8'b10000110;
            8'd116: cosine_value = 8'b10000110;
            8'd117: cosine_value = 8'b10000101;
            8'd118: cosine_value = 8'b10000100;
            8'd119: cosine_value = 8'b10000011;
            8'd120: cosine_value = 8'b10000010;
            8'd121: cosine_value = 8'b10000010;
            8'd122: cosine_value = 8'b10000001;
            8'd123: cosine_value = 8'b10000001;
            8'd124: cosine_value = 8'b10000001;
            8'd125: cosine_value = 8'b10000000;
            8'd126: cosine_value = 8'b10000000;
            8'd127: cosine_value = 8'b10000000;
            8'd128: cosine_value = 8'b10000000;
            8'd129: cosine_value = 8'b10000000;
            8'd130: cosine_value = 8'b10000000;
            8'd131: cosine_value = 8'b10000000;
            8'd132: cosine_value = 8'b10000001;
            8'd133: cosine_value = 8'b10000001;
            8'd134: cosine_value = 8'b10000001;
            8'd135: cosine_value = 8'b10000010;
            8'd136: cosine_value = 8'b10000010;
            8'd137: cosine_value = 8'b10000011;
            8'd138: cosine_value = 8'b10000100;
            8'd139: cosine_value = 8'b10000101;
            8'd140: cosine_value = 8'b10000110;
            8'd141: cosine_value = 8'b10000110;
            8'd142: cosine_value = 8'b10000111;
            8'd143: cosine_value = 8'b10001001;
            8'd144: cosine_value = 8'b10001010;
            8'd145: cosine_value = 8'b10001011;
            8'd146: cosine_value = 8'b10001100;
            8'd147: cosine_value = 8'b10001110;
            8'd148: cosine_value = 8'b10001111;
            8'd149: cosine_value = 8'b10010001;
            8'd150: cosine_value = 8'b10010010;
            8'd151: cosine_value = 8'b10010100;
            8'd152: cosine_value = 8'b10010110;
            8'd153: cosine_value = 8'b10010111;
            8'd154: cosine_value = 8'b10011001;
            8'd155: cosine_value = 8'b10011011;
            8'd156: cosine_value = 8'b10011101;
            8'd157: cosine_value = 8'b10011111;
            8'd158: cosine_value = 8'b10100001;
            8'd159: cosine_value = 8'b10100011;
            8'd160: cosine_value = 8'b10100101;
            8'd161: cosine_value = 8'b10101000;
            8'd162: cosine_value = 8'b10101010;
            8'd163: cosine_value = 8'b10101100;
            8'd164: cosine_value = 8'b10101111;
            8'd165: cosine_value = 8'b10110001;
            8'd166: cosine_value = 8'b10110100;
            8'd167: cosine_value = 8'b10110110;
            8'd168: cosine_value = 8'b10111001;
            8'd169: cosine_value = 8'b10111100;
            8'd170: cosine_value = 8'b10111110;
            8'd171: cosine_value = 8'b11000001;
            8'd172: cosine_value = 8'b11000100;
            8'd173: cosine_value = 8'b11000110;
            8'd174: cosine_value = 8'b11001001;
            8'd175: cosine_value = 8'b11001100;
            8'd176: cosine_value = 8'b11001111;
            8'd177: cosine_value = 8'b11010010;
            8'd178: cosine_value = 8'b11010101;
            8'd179: cosine_value = 8'b11011000;
            8'd180: cosine_value = 8'b11011011;
            8'd181: cosine_value = 8'b11011110;
            8'd182: cosine_value = 8'b11100001;
            8'd183: cosine_value = 8'b11100100;
            8'd184: cosine_value = 8'b11100111;
            8'd185: cosine_value = 8'b11101010;
            8'd186: cosine_value = 8'b11101101;
            8'd187: cosine_value = 8'b11110000;
            8'd188: cosine_value = 8'b11110011;
            8'd189: cosine_value = 8'b11110111;
            8'd190: cosine_value = 8'b11111010;
            8'd191: cosine_value = 8'b11111101;
            8'd192: cosine_value = 8'b00000000;
            8'd193: cosine_value = 8'b00000011;
            8'd194: cosine_value = 8'b00000110;
            8'd195: cosine_value = 8'b00001001;
            8'd196: cosine_value = 8'b00001101;
            8'd197: cosine_value = 8'b00010000;
            8'd198: cosine_value = 8'b00010011;
            8'd199: cosine_value = 8'b00010110;
            8'd200: cosine_value = 8'b00011001;
            8'd201: cosine_value = 8'b00011100;
            8'd202: cosine_value = 8'b00011111;
            8'd203: cosine_value = 8'b00100010;
            8'd204: cosine_value = 8'b00100101;
            8'd205: cosine_value = 8'b00101000;
            8'd206: cosine_value = 8'b00101011;
            8'd207: cosine_value = 8'b00101110;
            8'd208: cosine_value = 8'b00110001;
            8'd209: cosine_value = 8'b00110100;
            8'd210: cosine_value = 8'b00110111;
            8'd211: cosine_value = 8'b00111010;
            8'd212: cosine_value = 8'b00111100;
            8'd213: cosine_value = 8'b00111111;
            8'd214: cosine_value = 8'b01000010;
            8'd215: cosine_value = 8'b01000100;
            8'd216: cosine_value = 8'b01000111;
            8'd217: cosine_value = 8'b01001010;
            8'd218: cosine_value = 8'b01001100;
            8'd219: cosine_value = 8'b01001111;
            8'd220: cosine_value = 8'b01010001;
            8'd221: cosine_value = 8'b01010100;
            8'd222: cosine_value = 8'b01010110;
            8'd223: cosine_value = 8'b01011000;
            8'd224: cosine_value = 8'b01011011;
            8'd225: cosine_value = 8'b01011101;
            8'd226: cosine_value = 8'b01011111;
            8'd227: cosine_value = 8'b01100001;
            8'd228: cosine_value = 8'b01100011;
            8'd229: cosine_value = 8'b01100101;
            8'd230: cosine_value = 8'b01100111;
            8'd231: cosine_value = 8'b01101001;
            8'd232: cosine_value = 8'b01101010;
            8'd233: cosine_value = 8'b01101100;
            8'd234: cosine_value = 8'b01101110;
            8'd235: cosine_value = 8'b01101111;
            8'd236: cosine_value = 8'b01110001;
            8'd237: cosine_value = 8'b01110010;
            8'd238: cosine_value = 8'b01110100;
            8'd239: cosine_value = 8'b01110101;
            8'd240: cosine_value = 8'b01110110;
            8'd241: cosine_value = 8'b01110111;
            8'd242: cosine_value = 8'b01111001;
            8'd243: cosine_value = 8'b01111010;
            8'd244: cosine_value = 8'b01111010;
            8'd245: cosine_value = 8'b01111011;
            8'd246: cosine_value = 8'b01111100;
            8'd247: cosine_value = 8'b01111101;
            8'd248: cosine_value = 8'b01111110;
            8'd249: cosine_value = 8'b01111110;
            8'd250: cosine_value = 8'b01111111;
            8'd251: cosine_value = 8'b01111111;
            8'd252: cosine_value = 8'b01111111;
            8'd253: cosine_value = 8'b01111111;
            8'd254: cosine_value = 8'b01111111;
            8'd255: cosine_value = 8'b01111111;
            default: cosine_value = 8'd0;
        endcase
    end
endmodule



module my_waveform_gem (
    input clk,
    input reset,
    input signed [8:0] control,
    output [7:0] my_sine_out,
    output [7:0] my_cosine_out
);

    reg signed [8:0] phase_change;
    

    always @(posedge clk) begin
        if (reset) 
            phase_change <= 9'sd0;
        else
            phase_change <= phase_change + control;
    end

    // Instantiation for cosine LUT output
    wire [7:0] lut_entry = phase_change [7:0];

    Cosine_LUT cos_ut (
        .phase(lut_entry),
        .cosine_value(my_cosine_out)
    );

    // Instantiation for sine LUT output
    Cosine_LUT sin_ut (
        .phase(lut_entry + 8'd64),  // 90-degree phase shift equivalent in terms of entry number
        .cosine_value(my_sine_out)
    );


endmodule


module my_controller (
    input clk, 
    input reset,
    input [7:0] period,
    output reg signed [8:0] control
);


    reg [13:0] counter;
    reg [13:0] half_period; // The number of the clock cycles
    reg signed [8:0] control_hf;
    reg signed [8:0] control_lf;
    reg switch; // Help to make switch between the two frequency


    // Initialize the control signal for each frequency (high for hf and low for lf)
    initial begin
        control_hf = 9'sd6;
        control_lf = 9'sd1;

    end


    // Alternates the frequency between 2.3 MHz and 0.3 MHz with the input period
    // reset cases - reset and period change
    always @(posedge clk) begin
        if (reset) begin
            counter <= 14'd0;
            switch <= 1'b0;
            control <= control_hf;
            half_period <= period * 8'd50;
        end else begin
        // Alternate the frequency when counter reaches the number of cycles for each half period
        if (counter >= half_period - 1) begin
            counter <= 14'd0;
            switch <= ~switch;
            control <= (~switch) ? control_lf : control_hf;
        end else begin
            counter <= counter + 14'd1;
        end
        // $display("counter number is:\t", counter);
        // $display("switch is:\t", switch);
        end
    end

endmodule

EECS 598/Task4b_tb.v
`timescale 1ns/1ns
module my_waveform_gem_tb;


    reg clk;
    reg reset;
    reg [7:0] period;
    wire signed [8:0] control;
    wire [7:0] my_sine_out;
    wire [7:0] my_cosine_out;
    integer outfile;


    // The instantiation of my waveform generator
    my_waveform_gem uut1 (
        .clk(clk),
        .reset(reset),
        .control(control),
        .my_sine_out(my_sine_out),
        .my_cosine_out(my_cosine_out)
    );

    my_controller uut2 (
        .clk(clk),
        .reset(reset),
        .period(period),
        .control(control)
    );

    // Create a file to store the sine and cosine outputs
    initial begin
        outfile = $fopen("output_data.txt", "w");
    end


    // 100 MHz clock - 10 ns clock period (clock cycle)
    initial clk = 0;
    always #5 clk = ~clk;

    initial begin
    // Dump the simulation result to a VCD file
        $dumpfile("waveform.vcd");
        $dumpvars(0, my_waveform_gem_tb);

        reset = 1;
        period = 8'd16;
        #10;
        reset = 0;
        
        #100000;

        // // Start test 1 - 3.29 MHz
        // control = 9'sd8;
        // #800;   // Roughly 2 time periods

        // // Start test 2 - -1.35 MHz
        // control = -9'sd3;
        // #2000;  // Roughly 2 time periods

        // // Start test 3 - 0.43 MHz
        // control = 9'sd1;
        // #5000; // Roughly 2 time periods

        $finish;

    end

    // Store the sine and cosine outputs to the file
    always @(posedge clk) begin
        if (!reset) begin
            $fwrite(outfile, "%d, %d\n", my_sine_out, my_cosine_out);
        end
    end



    endmodule

EECS 598/waveform.vcd
$date
	Sun Sep 22 14:59:39 2024
$end
$version
	Icarus Verilog
$end
$timescale
	1ns
$end
$scope module my_waveform_gem_tb $end
$var wire 8 ! my_sine_out [7:0] $end
$var wire 8 " my_cosine_out [7:0] $end
$var wire 9 # control [8:0] $end
$var reg 1 $ clk $end
$var reg 8 % period [7:0] $end
$var reg 1 & reset $end
$var integer 32 ' outfile [31:0] $end
$scope module uut1 $end
$var wire 1 $ clk $end
$var wire 1 & reset $end
$var wire 8 ( my_sine_out [7:0] $end
$var wire 8 ) my_cosine_out [7:0] $end
$var wire 8 * lut_entry [7:0] $end
$var wire 9 + control [8:0] $end
$var reg 9 , phase_change [8:0] $end
$scope module cos_ut $end
$var wire 8 - phase [7:0] $end
$var reg 8 . cosine_value [7:0] $end
$upscope $end
$scope module sin_ut $end
$var wire 8 / phase [7:0] $end
$var reg 8 0 cosine_value [7:0] $end
$upscope $end
$upscope $end
$scope module uut2 $end
$var wire 1 $ clk $end
$var wire 8 1 period [7:0] $end
$var wire 1 & reset $end
$var reg 9 2 control [8:0] $end
$var reg 9 3 control_hf [8:0] $end
$var reg 9 4 control_lf [8:0] $end
$var reg 14 5 counter [13:0] $end
$var reg 14 6 half_period [13:0] $end
$var reg 1 7 switch $end
$upscope $end
$upscope $end
$enddefinitions $end
$comment Show the parameter values. $end
$dumpall
$end
#0
$dumpvars
x7
bx 6
bx 5
b1 4
b110 3
bx 2
b10000 1
bx 0
bx /
bx .
bx -
bx ,
bx +
bx *
bx )
bx (
b10000000000000000000000000000011 '
1&
b10000 %
0$
bx #
bx "
bx !
$end
#5
b0 !
b0 (
b0 0
b1111111 "
b1111111 )
b1111111 .
b1000000 /
b0 *
b0 -
b0 ,
b1100100000 6
b110 #
b110 +
b110 2
07
b0 5
1$
#10
0$
0&
#15
b11101101 !
b11101101 (
b11101101 0
b1000110 /
b110 *
b110 -
b1 5
b110 ,
1$
#20
0$
#25
b11011011 !
b11011011 (
b11011011 0
b1111010 "
b1111010 )
b1111010 .
b1001100 /
b1100 *
b1100 -
b1100 ,
b10 5
1$
#30
0$
#35
b11001001 !
b11001001 (
b11001001 0
b1110100 "
b1110100 )
b1110100 .
b1010010 /
b10010 *
b10010 -
b11 5
b10010 ,
1$
#40
0$
#45
b10111001 !
b10111001 (
b10111001 0
b1101010 "
b1101010 )
b1101010 .
b1011000 /
b11000 *
b11000 -
b11000 ,
b100 5
1$
#50
0$
#55
b10101010 !
b10101010 (
b10101010 0
b1011111 "
b1011111 )
b1011111 .
b1011110 /
b11110 *
b11110 -
b101 5
b11110 ,
1$
#60
0$
#65
b10011101 !
b10011101 (
b10011101 0
b1010001 "
b1010001 )
b1010001 .
b1100100 /
b100100 *
b100100 -
b100100 ,
b110 5
1$
#70
0$
#75
b10010010 !
b10010010 (
b10010010 0
b1000010 "
b1000010 )
b1000010 .
b1101010 /
b101010 *
b101010 -
b111 5
b101010 ,
1$
#80
0$
#85
b10001010 !
b10001010 (
b10001010 0
b110001 "
b110001 )
b110001 .
b1110000 /
b110000 *
b110000 -
b110000 ,
b1000 5
1$
#90
0$
#95
b10000100 !
b10000100 (
b10000100 0
b11111 "
b11111 )
b11111 .
b1110110 /
b110110 *
b110110 -
b1001 5
b110110 ,
1$
#100
0$
#105
b10000001 !
b10000001 (
b10000001 0
b1101 "
b1101 )
b1101 .
b1111100 /
b111100 *
b111100 -
b111100 ,
b1010 5
1$
#110
0$
#115
b10000000 !
b10000000 (
b10000000 0
b11111010 "
b11111010 )
b11111010 .
b10000010 /
b1000010 *
b1000010 -
b1011 5
b1000010 ,
1$
#120
0$
#125
b10000010 !
b10000010 (
b10000010 0
b11100111 "
b11100111 )
b11100111 .
b10001000 /
b1001000 *
b1001000 -
b1001000 ,
b1100 5
1$
#130
0$
#135
b10000111 !
b10000111 (
b10000111 0
b11010101 "
b11010101 )
b11010101 .
b10001110 /
b1001110 *
b1001110 -
b1101 5
b1001110 ,
1$
#140
0$
#145
b10001111 !
b10001111 (
b10001111 0
b11000100 "
b11000100 )
b11000100 .
b10010100 /
b1010100 *
b1010100 -
b1010100 ,
b1110 5
1$
#150
0$
#155
b10011001 !
b10011001 (
b10011001 0
b10110100 "
b10110100 )
b10110100 .
b10011010 /
b1011010 *
b1011010 -
b1111 5
b1011010 ,
1$
#160
0$
#165
b10100101 !
b10100101 (
b10100101 0
b10100101 "
b10100101 )
b10100101 .
b10100000 /
b1100000 *
b1100000 -
b1100000 ,
b10000 5
1$
#170
0$
#175
b10110100 !
b10110100 (
b10110100 0
b10011001 "
b10011001 )
b10011001 .
b10100110 /
b1100110 *
b1100110 -
b10001 5
b1100110 ,
1$
#180
0$
#185
b11000100 !
b11000100 (
b11000100 0
b10001111 "
b10001111 )
b10001111 .
b10101100 /
b1101100 *
b1101100 -
b1101100 ,
b10010 5
1$
#190
0$
#195
b11010101 !
b11010101 (
b11010101 0
b10000111 "
b10000111 )
b10000111 .
b10110010 /
b1110010 *
b1110010 -
b10011 5
b1110010 ,
1$
#200
0$
#205
b11100111 !
b11100111 (
b11100111 0
b10000010 "
b10000010 )
b10000010 .
b10111000 /
b1111000 *
b1111000 -
b1111000 ,
b10100 5
1$
#210
0$
#215
b11111010 !
b11111010 (
b11111010 0
b10000000 "
b10000000 )
b10000000 .
b10111110 /
b1111110 *
b1111110 -
b10101 5
b1111110 ,
1$
#220
0$
#225
b1101 !
b1101 (
b1101 0
b10000001 "
b10000001 )
b10000001 .
b11000100 /
b10000100 *
b10000100 -
b10000100 ,
b10110 5
1$
#230
0$
#235
b11111 !
b11111 (
b11111 0
b10000100 "
b10000100 )
b10000100 .
b11001010 /
b10001010 *
b10001010 -
b10111 5
b10001010 ,
1$
#240
0$
#245
b110001 !
b110001 (
b110001 0
b10001010 "
b10001010 )
b10001010 .
b11010000 /
b10010000 *
b10010000 -
b10010000 ,
b11000 5
1$
#250
0$
#255
b1000010 !
b1000010 (
b1000010 0
b10010010 "
b10010010 )
b10010010 .
b11010110 /
b10010110 *
b10010110 -
b11001 5
b10010110 ,
1$
#260
0$
#265
b1010001 !
b1010001 (
b1010001 0
b10011101 "
b10011101 )
b10011101 .
b11011100 /
b10011100 *
b10011100 -
b10011100 ,
b11010 5
1$
#270
0$
#275
b1011111 !
b1011111 (
b1011111 0
b10101010 "
b10101010 )
b10101010 .
b11100010 /
b10100010 *
b10100010 -
b11011 5
b10100010 ,
1$
#280
0$
#285
b1101010 !
b1101010 (
b1101010 0
b10111001 "
b10111001 )
b10111001 .
b11101000 /
b10101000 *
b10101000 -
b10101000 ,
b11100 5
1$
#290
0$
#295
b1110100 !
b1110100 (
b1110100 0
b11001001 "
b11001001 )
b11001001 .
b11101110 /
b10101110 *
b10101110 -
b11101 5
b10101110 ,
1$
#300
0$
#305
b1111010 !
b1111010 (
b1111010 0
b11011011 "
b11011011 )
b11011011 .
b11110100 /
b10110100 *
b10110100 -
b10110100 ,
b11110 5
1$
#310
0$
#315
b1111111 !
b1111111 (
b1111111 0
b11101101 "
b11101101 )
b11101101 .
b11111010 /
b10111010 *
b10111010 -
b11111 5
b10111010 ,
1$
#320
0$
#325
b0 "
b0 )
b0 .
b0 /
b11000000 *
b11000000 -
b11000000 ,
b100000 5
1$
#330
0$
#335
b10011 "
b10011 )
b10011 .
b110 /
b11000110 *
b11000110 -
b100001 5
b11000110 ,
1$
#340
0$
#345
b1111010 !
b1111010 (
b1111010 0
b100101 "
b100101 )
b100101 .
b1100 /
b11001100 *
b11001100 -
b11001100 ,
b100010 5
1$
#350
0$
#355
b1110100 !
b1110100 (
b1110100 0
b110111 "
b110111 )
b110111 .
b10010 /
b11010010 *
b11010010 -
b100011 5
b11010010 ,
1$
#360
0$
#365
b1101010 !
b1101010 (
b1101010 0
b1000111 "
b1000111 )
b1000111 .
b11000 /
b11011000 *
b11011000 -
b11011000 ,
b100100 5
1$
#370
0$
#375
b1011111 !
b1011111 (
b1011111 0
b1010110 "
b1010110 )
b1010110 .
b11110 /
b11011110 *
b11011110 -
b100101 5
b11011110 ,
1$
#380
0$
#385
b1010001 !
b1010001 (
b1010001 0
b1100011 "
b1100011 )
b1100011 .
b100100 /
b11100100 *
b11100100 -
b11100100 ,
b100110 5
1$
#390
0$
#395
b1000010 !
b1000010 (
b1000010 0
b1101110 "
b1101110 )
b1101110 .
b101010 /
b11101010 *
b11101010 -
b100111 5
b11101010 ,
1$
#400
0$
#405
b110001 !
b110001 (
b110001 0
b1110110 "
b1110110 )
b1110110 .
b110000 /
b11110000 *
b11110000 -
b11110000 ,
b101000 5
1$
#410
0$
#415
b11111 !
b11111 (
b11111 0
b1111100 "
b1111100 )
b1111100 .
b110110 /
b11110110 *
b11110110 -
b101001 5
b11110110 ,
1$
#420
0$
#425
b1101 !
b1101 (
b1101 0
b1111111 "
b1111111 )
b1111111 .
b111100 /
b11111100 *
b11111100 -
b11111100 ,
b101010 5
1$
#430
0$
#435
b11111010 !
b11111010 (
b11111010 0
b1000010 /
b10 *
b10 -
b101011 5
b100000010 ,
1$
#440
0$
#445
b11100111 !
b11100111 (
b11100111 0
b1111110 "
b1111110 )
b1111110 .
b1001000 /
b1000 *
b1000 -
b100001000 ,
b101100 5
1$
#450
0$
#455
b11010101 !
b11010101 (
b11010101 0
b1111001 "
b1111001 )
b1111001 .
b1001110 /
b1110 *
b1110 -
b101101 5
b100001110 ,
1$
#460
0$
#465
b11000100 !
b11000100 (
b11000100 0
b1110001 "
b1110001 )
b1110001 .
b1010100 /
b10100 *
b10100 -
b100010100 ,
b101110 5
1$
#470
0$
#475
b10110100 !
b10110100 (
b10110100 0
b1100111 "
b1100111 )
b1100111 .
b1011010 /
b11010 *
b11010 -
b101111 5
b100011010 ,
1$
#480
0$
#485
b10100101 !
b10100101 (
b10100101 0
b1011011 "
b1011011 )
b1011011 .
b1100000 /
b100000 *
b100000 -
b100100000 ,
b110000 5
1$
#490
0$
#495
b10011001 !
b10011001 (
b10011001 0
b1001100 "
b1001100 )
b1001100 .
b1100110 /
b100110 *
b100110 -
b110001 5
b100100110 ,
1$
#500
0$
#505
b10001111 !
b10001111 (
b10001111 0
b111100 "
b111100 )
b111100 .
b1101100 /
b101100 *
b101100 -
b100101100 ,
b110010 5
1$
#510
0$
#515
b10000111 !
b10000111 (
b10000111 0
b101011 "
b101011 )
b101011 .
b1110010 /
b110010 *
b110010 -
b110011 5
b100110010 ,
1$
#520
0$
#525
b10000010 !
b10000010 (
b10000010 0
b11001 "
b11001 )
b11001 .
b1111000 /
b111000 *
b111000 -
b100111000 ,
b110100 5
1$
#530
0$
#535
b10000000 !
b10000000 (
b10000000 0
b110 "
b110 )
b110 .
b1111110 /
b111110 *
b111110 -
b110101 5
b100111110 ,
1$
#540
0$
#545
b10000001 !
b10000001 (
b10000001 0
b11110011 "
b11110011 )
b11110011 .
b10000100 /
b1000100 *
b1000100 -
b101000100 ,
b110110 5
1$
#550
0$
#555
b10000100 !
b10000100 (
b10000100 0
b11100001 "
b11100001 )
b11100001 .
b10001010 /
b1001010 *
b1001010 -
b110111 5
b101001010 ,
1$
#560
0$
#565
b10001010 !
b10001010 (
b10001010 0
b11001111 "
b11001111 )
b11001111 .
b10010000 /
b1010000 *
b1010000 -
b101010000 ,
b111000 5
1$
#570
0$
#575
b10010010 !
b10010010 (
b10010010 0
b10111110 "
b10111110 )
b10111110 .
b10010110 /
b1010110 *
b1010110 -
b111001 5
b101010110 ,
1$
#580
0$
#585
b10011101 !
b10011101 (
b10011101 0
b10101111 "
b10101111 )
b10101111 .
b10011100 /
b1011100 *
b1011100 -
b101011100 ,
b111010 5
1$
#590
0$
#595
b10101010 !
b10101010 (
b10101010 0
b10100001 "
b10100001 )
b10100001 .
b10100010 /
b1100010 *
b1100010 -
b111011 5
b101100010 ,
1$
#600
0$
#605
b10111001 !
b10111001 (
b10111001 0
b10010110 "
b10010110 )
b10010110 .
b10101000 /
b1101000 *
b1101000 -
b101101000 ,
b111100 5
1$
#610
0$
#615
b11001001 !
b11001001 (
b11001001 0
b10001100 "
b10001100 )
b10001100 .
b10101110 /
b1101110 *
b1101110 -
b111101 5
b101101110 ,
1$
#620
0$
#625
b11011011 !
b11011011 (
b11011011 0
b10000110 "
b10000110 )
b10000110 .
b10110100 /
b1110100 *
b1110100 -
b101110100 ,
b111110 5
1$
#630
0$
#635
b11101101 !
b11101101 (
b11101101 0
b10000001 "
b10000001 )
b10000001 .
b10111010 /
b1111010 *
b1111010 -
b111111 5
b101111010 ,
1$
#640
0$
#645
b0 !
b0 (
b0 0
b10000000 "
b10000000 )
b10000000 .
b11000000 /
b10000000 *
b10000000 -
b110000000 ,
b1000000 5
1$
#650
0$
#655
b10011 !
b10011 (
b10011 0
b10000001 "
b10000001 )
b10000001 .
b11000110 /
b10000110 *
b10000110 -
b1000001 5
b110000110 ,
1$
#660
0$
#665
b100101 !
b100101 (
b100101 0
b10000110 "
b10000110 )
b10000110 .
b11001100 /
b10001100 *
b10001100 -
b110001100 ,
b1000010 5
1$
#670
0$
#675
b110111 !
b110111 (
b110111 0
b10001100 "
b10001100 )
b10001100 .
b11010010 /
b10010010 *
b10010010 -
b1000011 5
b110010010 ,
1$
#680
0$
#685
b1000111 !
b1000111 (
b1000111 0
b10010110 "
b10010110 )
b10010110 .
b11011000 /
b10011000 *
b10011000 -
b110011000 ,
b1000100 5
1$
#690
0$
#695
b1010110 !
b1010110 (
b1010110 0
b10100001 "
b10100001 )
b10100001 .
b11011110 /
b10011110 *
b10011110 -
b1000101 5
b110011110 ,
1$
#700
0$
#705
b1100011 !
b1100011 (
b1100011 0
b10101111 "
b10101111 )
b10101111 .
b11100100 /
b10100100 *
b10100100 -
b110100100 ,
b1000110 5
1$
#710
0$
#715
b1101110 !
b1101110 (
b1101110 0
b10111110 "
b10111110 )
b10111110 .
b11101010 /
b10101010 *
b10101010 -
b1000111 5
b110101010 ,
1$
#720
0$
#725
b1110110 !
b1110110 (
b1110110 0
b11001111 "
b11001111 )
b11001111 .
b11110000 /
b10110000 *
b10110000 -
b110110000 ,
b1001000 5
1$
#730
0$
#735
b1111100 !
b1111100 (
b1111100 0
b11100001 "
b11100001 )
b11100001 .
b11110110 /
b10110110 *
b10110110 -
b1001001 5
b110110110 ,
1$
#740
0$
#745
b1111111 !
b1111111 (
b1111111 0
b11110011 "
b11110011 )
b11110011 .
b11111100 /
b10111100 *
b10111100 -
b110111100 ,
b1001010 5
1$
#750
0$
#755
b110 "
b110 )
b110 .
b10 /
b11000010 *
b11000010 -
b1001011 5
b111000010 ,
1$
#760
0$
#765
b1111110 !
b1111110 (
b1111110 0
b11001 "
b11001 )
b11001 .
b1000 /
b11001000 *
b11001000 -
b111001000 ,
b1001100 5
1$
#770
0$
#775
b1111001 !
b1111001 (
b1111001 0
b101011 "
b101011 )
b101011 .
b1110 /
b11001110 *
b11001110 -
b1001101 5
b111001110 ,
1$
#780
0$
#785
b1110001 !
b1110001 (
b1110001 0
b111100 "
b111100 )
b111100 .
b10100 /
b11010100 *
b11010100 -
b111010100 ,
b1001110 5
1$
#790
0$
#795
b1100111 !
b1100111 (
b1100111 0
b1001100 "
b1001100 )
b1001100 .
b11010 /
b11011010 *
b11011010 -
b1001111 5
b111011010 ,
1$
#800
0$
#805
b1011011 !
b1011011 (
b1011011 0
b1011011 "
b1011011 )
b1011011 .
b100000 /
b11100000 *
b11100000 -
b111100000 ,
b1010000 5
1$
#810
0$
#815
b1001100 !
b1001100 (
b1001100 0
b1100111 "
b1100111 )
b1100111 .
b100110 /
b11100110 *
b11100110 -
b1010001 5
b111100110 ,
1$
#820
0$
#825
b111100 !
b111100 (
b111100 0
b1110001 "
b1110001 )
b1110001 .
b101100 /
b11101100 *
b11101100 -
b111101100 ,
b1010010 5
1$
#830
0$
